Workbook

Sheet DESARROLLADOR
B1: ID | C1: ACTIVO | D1: NOMBRE | E1: RAZON SOCIAL | F1: RFC | G1: DOMICILIO | H1: ANTIGUEDAD | J1: TIPOS DE DESARROLLOS | K1: REPRESENTANTELEGAL | L1: VENTAS | O1: PAGOS | R1: COMERCIALIZADORA | S1: LEGALES
B2: 1 | C2: Si | D2: CREARE | E2: Creare Desarrollos SA de CV | F2: DEC210330TY8 | G2: Eugenio Garza Sada 3820, Col. Ms Palomas, Monterrey N.L. 64780 | H2: 44114 | I2: =(TODAY()-H2)/30.4 -> 63.486842 | J2: Residencial, Comercial, Salud | K2: Jorge Gozalez Perez | L2: Karla Gomez Peña | M2: karla@creare.com.mx | N2: 8181232345 | O2: Ernesto Lozano Gamez | P2: ernesto@creare.com.mx | Q2: 8123234555 | R2: Birlok | S2: LEGALES
A3: Admin
A4: Updater
A5: Profiler
A6: Finanzas | S6: Convenios NO
A7: Asesor Interno | S7: Convenios NO
A8: Desarrollador
J9: N/A | K9: N/A | L9: N/A | M9: N/A | N9: N/A | O9: N/A | P9: N/A | Q9: N/A | R9: N/A

Sheet DESARROLLOS
D1: DESARROLLADOR | E1: DESARROLLO | F1: CIUDAD | G1: ZONA 1 | H1: ZONA 2 | I1: ZONA 3 | J1: TIPO | K1: TORRES | L1: NIVELES | M1: AMENIDADES | N1: EFICIENCIA | O1: OTROS | P1: TAMAÑOS | R1: RECÁMARAS | T1: LOCK OFF | U1: COMO SE ENTREGAN | V1: UNIDADES Y METROS CUADRADOS | AE1: INICIO PREVENTA | AF1: TIEMPO TRANSCURR. | AG1: UNIDADES VENDIDAS | AH1: PORC. | AI1: INICIO CONSTR. | AJ1: TIEMPO TRANSUCRR. | AK1: INICIO CONSTR. Real | AL1: ENTREGA PROYECTADA | AM1: TIEMPO | AN1: ENTREGA REAL | AV1: COMERIALIZADORA | AW1: DESPACHO DE ARQUITECTOS | AX1: LOCATION | AY1: LEGALES | AZ1: VENTA
P2: DESDE | Q2: HASTA | R2: DESDE | S2: HASTA | V2: DEPARTAMENTOS | X2: LOCALES | Z2: OFICINAS | AB2: SALUD | AM2: RESTANTE | AP2: VENTAS | AS2: PAGOS
B4: 1 | C4: Si | D4: KOINOX | E4: Midtown | F4: CDMX | G4: EEE | H4: EEE | I4: FFF | J4: Residencial | K4: 1 | L4: 15 | P4: 88 | Q4: 88 | R4: 2 | S4: 2 | T4: Si | V4: 20 | W4: 1760 | X4: 3 | Y4: 160 | AE4: 44501 | AF4: =INT(((TODAY()-AE4)/365)) & " años y " & INT((((TODAY()-AE4)/365)-INT(((TODAY()-AE4)/365)))*12) & " meses" -> 4 años y 2 meses | AG4: 15 | AH4: =AG4/V4 -> 0.75 | AI4: 44927 | AJ4: =INT(((TODAY()-AI4)/365)) & " años y " & INT((((TODAY()-AI4)/365)-INT(((TODAY()-AI4)/365)))*12) & " meses" -> 3 años y 0 meses | AL4: 45566 | AN4: 45566 | AP4: Karla Gomez Peña | AQ4: karla@creare.com.mx | AR4: 8181232345 | AS4: Ernesto Lozano Gamez | AT4: ernesto@creare.com.mx | AU4: 8123234555 | AV4: Birlok | AW4: Arquitectos del Norte
A5: Admin
A6: Updater
A7: Profiler
A8: Finanzas | AY8: Solo Convenios
A9: Asesor | AY9: Sin Convenios
A10: Desarrollador
V11: N/A | W11: N/A | X11: N/A | Y11: N/A | Z11: N/A | AA11: N/A | AB11: N/A | AC11: N/A | AP11: N/A | AQ11: N/A | AR11: N/A | AS11: N/A | AT11: N/A | AU11: N/A | AV11: N/A | AW11: N/A
AP12: Mismo | AQ12: Mismo | AR12: Mismo | AS12: Mismo | AT12: Mismo | AU12: Mismo | AV12: Mismo

Sheet TIPOLOGIAS
H1: GENERALES | L1: PRECIO | W1: DISTRIBUCIÓN | AO1: ESQUEMA DE PAGO | BA1: GASTOS DESPUÉS DE LA ENTREGA | BI1: 0.105 | BJ1: 15 | BK1: CRÉDITO HIPOTECARIO | BO1: MANTENIMIENTO | BX1: 0.07 | BY1: RENTA | CA1: 11 | CD1: INVERSIÓN | CI1: 0.07 | CJ1: PLUSVALÍA
C2: CIUDAD | D2: ZONA | E2: DESARROLLADOR | F2: DESARROLLO | H2: TIPO | I2: NIVEL | J2: VISTA | L2: TAMAÑO | M2: PRECIO | N2: BONO | O2: % | P2: MONTO | Q2: PRECIO FINAL | R2: PRECIO/M2 | T2: CAPITAL SEMILLA | U2: PROMO | W2: REC | X2: FLEX | Y2: BAÑOS | Z2: SALA | AA2: COMEDRO | AB2: COCINAS | AC2: BALCÓN | AE2: TERRAZA | AG2: LAVANDERÍA | AH2: SERV. | AI2: CAJÓN | AJ2: EXTRA | AK2: PRECIO | AL2: BODEGA | AO2: INICIAL | AP2: MONTO | AQ2: EN PLAZO | AR2: MONTO | AS2: MESES | AT2: MENS. | AU2: TOT. ENG. | AV2: RESTO | AY2: ENTREGA | BA2: ISAI | BB2: NOTARIO | BC2: EQUIPO | BD2: MUEBLES | BE2: TOTAL | BG2: MONTO | BH2: INICIA | BI2: TASA | BJ2: AÑOS | BK2: MENSUALIDAD | BL2: TERMINA | BM2: TOTAL | BO2: M2 | BP2: INICIAL | BQ2: FECHA | BR2: FINAL | BS2: FECHA | BT2: TOTAL | BV2: INICIAL | BW2: FECHA | BX2: TASA | BY2: FINAL | BZ2: FECHA | CA2: MESES | CB2: TOTAL | CD2: TOTAL | CE2: NETA | CF2: MENSUAL | CG2: TASA | CI2: TASA | CJ2: DÍAS | CK2: MESES | CL2: AÑOS | CM2: TOTAL | CN2: MONTO FINAL
A3: 1 | B3: Si | C3: Monterrey | D3: San José Tec | E3: AISEN | F3: Livita 20 | H3: A | I3: 4 | J3: Obispado | L3: 88 | M3: 4782888 | N3: No | O3: =P3/M3 -> 0.02090787 | P3: 100000 | Q3: =IF(N3="No",M3,M3-P3) -> 4782888 | R3: =Q3/L3 -> 54351 | T3: No | U3: No | W3: 2 | X3: No | Y3: 2 | Z3: Si | AA3: Si | AB3: Si | AC3: Si | AD3: 2.34 | AE3: No | AG3: Si | AH3: No | AI3: 2 | AJ3: No | AL3: Si | AM3: 1.23 | AO3: 0.1 | AP3: =M3*AO3 -> 478288.8 | AQ3: 0.1 | AR3: =AQ3*M3 -> 478288.8 | AS3: 21 | AT3: =AR3/AS3 -> 22775.657 | AU3: =AP3+AR3 -> 956577.6 | AV3: =1-AO3-AQ3 -> 0.8 | AW3: =M3-AP3-(AS3*AT3) -> 3826310.4 | AY3: 45597 | BA3: =M3*0.03 -> 143486.64 | BB3: =M3*0.02 -> 95657.76 | BC3: 300000 | BD3: 150000 | BE3: =BA3+BB3+BC3+BD3 -> 689144.4 | BG3: =AW3 -> 3826310.4 | BH3: =AY3+31 -> 45628 | BI3: =BI$1 -> 0.105 | BJ3: =BJ$1 -> 15 | BK3: =PMT(BI3/12,BJ3*12,-AW3) -> 42295.994 | BL3: =TIPOLOGIAS!AY3+(TIPOLOGIAS!BJ3*365.25) -> 51075.75 | BM3: =BK3*BJ3*12 -> 7613278.9 | BO3: 40 | BP3: =L3*BO3 -> 3520 | BQ3: =AY3+31 -> 45628 | BR3: =FV(BX3,BJ$1,0,-BP3) -> 9711.791 | BS3: =TIPOLOGIAS!AY3+(TIPOLOGIAS!BJ3*365.25) -> 51075.75 | BT3: =FV(BX3,BJ$1,-BP3*12,0) -> 1061449.9 | BV3: 24500 | BW3: =TIPOLOGIAS!AY3+62 -> 45659 | BX3: =BX$1 -> 0.07 | BY3: =FV(BX3,BJ$1,0,-BV3) -> 67596.273 | BZ3: =TIPOLOGIAS!AY3+(TIPOLOGIAS!BJ3*365.25) -> 51075.75 | CA3: =CA$1 -> 11 | CB3: =FV(BX3,BJ3,-BV3*CA3,0)-(2*BV3) -> 6723271.4 | CD3: =AU3+BE3+BM3+BT3 -> 10320451 | CE3: =CD3-CB3 -> 3597179.4 | CF3: =CE3/CK3 -> 21759.656 | CG3: =(RATE(CK3,-CF3,0,CN3))*12 -> 0.15295236 | CI3: =CI$1 -> 0.07 | CJ3: =(AY3-TODAY()+(BJ$1*365.25)) -> 5031.75 | CK3: =CJ3/30.4375 -> 165.31417 | CL3: =CK3/12 -> 13.776181 | CM3: =INT(CL3) & " años y " & INT((CL3-INT(CL3))*12) & " meses" -> 13 años y 9 meses | CN3: =FV(CI3,((AY3-TODAY())/365.25)+BJ$1,0,-Q3) -> 12147487
A4: 2 | B4: Si | C4: Monterrey | D4: Valle Poniente | E4: LANDWORK | F4: Mun | H4: B | I4: 22 | J4: Sierra Madre y Huasteca | L4: =92.24+4.5 -> 96.74 | M4: =5202945+81000 -> 5283945 | N4: Si | O4: =P4/M4 -> 0.0056775761 | P4: 30000 | Q4: =IF(N4="No",M4,M4-P4) -> 5253945 | R4: =Q4/L4 -> 54309.955 | T4: No | U4: No | W4: 2 | X4: No | Y4: 2 | Z4: Si | AA4: Si | AB4: Si | AC4: No | AE4: No | AG4: Si | AH4: No | AI4: 2 | AJ4: No | AL4: Si | AM4: 4.5 | AO4: 0.05 | AP4: =M4*AO4 -> 264197.25 | AQ4: 0.05 | AR4: =AQ4*M4 -> 264197.25 | AS4: 18 | AT4: =AR4/AS4 -> 14677.625 | AU4: =AP4+AR4 -> 528394.5 | AV4: =1-AO4-AQ4 -> 0.9 | AW4: =M4-AP4-(AS4*AT4) -> 4755550.5 | AY4: 45627 | BA4: =M4*0.03 -> 158518.35 | BB4: =M4*0.02 -> 105678.9 | BC4: 180000 | BD4: 125000 | BE4: =BA4+BB4+BC4+BD4 -> 569197.25 | BG4: =AW4 -> 4755550.5 | BH4: =AY4+31 -> 45658 | BI4: =BI$1 -> 0.105 | BJ4: =BJ$1 -> 15 | BK4: =PMT(BI4/12,BJ4*12,-AW4) -> 52567.804 | BL4: =TIPOLOGIAS!AY4+(TIPOLOGIAS!BJ4*365.25) -> 51105.75 | BM4: =BK4*BJ4*12 -> 9462204.7 | BO4: 40 | BP4: =L4*BO4 -> 3869.6 | BQ4: =AY4+31 -> 45658 | BR4: =FV(BX4,BJ$1,0,-BP4) -> 10676.348 | BS4: =TIPOLOGIAS!AY4+(TIPOLOGIAS!BJ4*365.25) -> 51105.75 | BT4: =FV(BX4,BJ$1,-BP4*12,0) -> 1166871.2 | BW4: =TIPOLOGIAS!AY4+62 -> 45689 | BX4: =BX$1 -> 0.07 | BY4: =FV(BX4,BJ$1,0,-BV4) -> 0 | BZ4: =TIPOLOGIAS!AY4+(TIPOLOGIAS!BJ4*365.25) -> 51105.75 | CA4: =CA$1 -> 11 | CB4: =FV(BX4,BJ4,-BV4*CA4,0)-(2*BV4) -> 0 | CD4: =AU4+BE4+BM4+BT4 -> 11726668 | CE4: =CD4-CB4 -> 11726668 | CF4: =CE4/CK4 -> 70515.226 | CG4: =(RATE(CK4,-CF4,0,CN4))*12 -> 0.019154207 | CI4: =CI$1 -> 0.07 | CJ4: =(AY4-TODAY()+(BJ$1*365.25)) -> 5061.75 | CK4: =CJ4/30.4375 -> 166.29979 | CL4: =CK4/12 -> 13.858316 | CM4: =INT(CL4) & " años y " & INT((CL4-INT(CL4))*12) & " meses" -> 13 años y 10 meses | CN4: =FV(CI4,((AY4-TODAY())/365.25)+BJ$1,0,-Q4) -> 13418229
C8: PERFILES | D8: PUEDE MODIFICAR
C9: ADMIN
C10: UPDATER
C11: ASESOR
C12: DESARROLLADOR
C16: Son 3 vistas:
C17: Todo | E17: Admin y Asesor
C18: Naranja | E18: Admin y Updater
C19: Verde | E19: Todos

Sheet DESARROLLOS (2)
B1: DESARROLLADOR | C1: DESARROLLO | D1: CIUDAD | E1: ZONA 1 | F1: ZONA 2 | G1: ZONA 3 | H1: TIPO | I1: TORRES | J1: NIVELES | K1: AMENIDADES | L1: EFICIENCIA | M1: OTROS | N1: TAMAÑOS | P1: RECÁMARAS | R1: LOCK OFF | S1: COMO SE ENTREGAN | T1: UNIDADES Y METROS CUADRADOS | AB1: RENDERS | AC1: LOGO Y NOMBRE? | AD1: FECHA DE ENTREGA
N2: DESDE | O2: HASTA | P2: DESDE | Q2: HASTA | T2: DEPARTAMENTOS | V2: LOCALES | X2: OFICINAS | Z2: SALUD
A4: 1 | B4: Creare | C4: Arena Fundidora | D4: MONTERREY | E4: SAN JOSÉ TEC | F4: VALLE | G4: Fundidora | H4: Residencial | I4: 1 | J4: 15 | N4: 88 | O4: 88 | P4: 2 | Q4: 2 | R4: Si | T4: 20 | U4: 1760 | V4: 3 | W4: 160
A5: 2
A6: 3
A7: 4
A8: 5
A9: 6
A10: 7
A11: 8
A12: 9
A13: 10
A14: 11
A15: 12
A16: 13
... A103: 100

Sheet TIPOLOGÍAS
I1: GENERALES | M1: PRECIO | X1: DISTRIBUCIÓN | AP1: ESQUEMA DE PAGO | BB1: GASTOS DESPUÉS DE LA ENTREGA | BJ1: 0.12 | BK1: 15 | BL1: CRÉDITO HIPOTECARIO | BP1: MANTENIMIENTO | BY1: 0.068 | BZ1: RENTA | CB1: 11 | CE1: INVERSIÓN | CJ1: 0.068 | CK1: PLUSVALÍA | CP1: VENTA
D2: CIUDAD | E2: ZONA | F2: DESARROLLADOR | G2: DESARROLLO | I2: TIPO | J2: NIVEL | K2: VISTA | M2: TAMAÑO | N2: PRECIO | O2: BONO | P2: % | Q2: MONTO | R2: PRECIO FINAL | S2: PRECIO/M2 | U2: CAP. | V2: PROMO | X2: REC | Y2: FLEX | Z2: BAÑOS | AA2: SALA | AB2: COM. | AC2: COC. | AD2: BALCÓN | AF2: TERRAZA | AH2: LAV. | AI2: SERV. | AJ2: CAJ. | AK2: EXTRA | AL2: PRECIO | AM2: BODEGA | AP2: INICIAL | AQ2: MONTO | AR2: EN PLAZO | AS2: MONTO | AT2: MESES | AU2: MENS. | AV2: TOT. ENG. | AW2: RESTO | AZ2: ENTREGA | BB2: ISAI | BC2: NOTARIO | BD2: EQUIPO | BE2: MUEBLES | BF2: TOTAL | BH2: MONTO | BI2: INICIA | BJ2: TASA | BK2: AÑOS | BL2: MENS. | BM2: TERMINA | BN2: TOTAL | BP2: M2 | BQ2: INICIAL | BR2: FECHA | BS2: FINAL | BT2: FECHA | BU2: TOTAL | BW2: INICIAL | BX2: FECHA | BY2: TASA | BZ2: FINAL | CA2: FECHA | CB2: MESES | CC2: TOTAL | CE2: TOTAL | CF2: NETA | CG2: MENSUAL | CH2: TASA | CJ2: TASA | CK2: DÍAS | CL2: MESES | CM2: AÑOS | CN2: TOTAL | CO2: MONTO FINAL
B3: 1 | C3: Si | D3: Monterrey | E3: Cumbres | F3: Quantium | G3: Lívita 20 | I3: A | J3: 4 | K3: Norte | M3: 88 | N3: 4782888 | O3: Si | P3: =Q3/N3 -> 0.02090787 | Q3: 100000 | R3: =IF(O3="No",N3,N3-Q3) -> 4682888 | S3: =R3/M3 -> 53214.636 | U3: No | V3: No | X3: 2 | Y3: No | Z3: 2 | AA3: Si | AB3: Si | AC3: Si | AD3: Si | AE3: 2.34 | AF3: Si | AH3: Si | AI3: No | AJ3: 2 | AK3: No | AM3: Si | AN3: 1.23 | AP3: 0.1 | AQ3: =N3*AP3 -> 478288.8 | AR3: 0.1 | AS3: =AR3*N3 -> 478288.8 | AT3: 21 | AU3: =AS3/AT3 -> 22775.657 | AV3: =AQ3+AS3 -> 956577.6 | AW3: =1-AP3-AR3 -> 0.8 | AX3: =N3-AQ3-(AT3*AU3) -> 3826310.4 | AZ3: 45597 | BB3: =N3*0.03 -> 143486.64 | BC3: =N3*0.02 -> 95657.76 | BD3: 300000 | BE3: 150000 | BF3: =BB3+BC3+BD3+BE3 -> 689144.4 | BH3: =AX3 -> 3826310.4 | BI3: =AZ3+31 -> 45628 | BJ3: =BJ$1 -> 0.12 | BK3: =BK$1 -> 15 | BL3: =PMT(BJ3/12,BK3*12,-AX3) -> 45922.155 | BM3: =TIPOLOGÍAS!AZ3+(TIPOLOGÍAS!BK3*365.25) -> 51075.75 | BN3: =BL3*BK3*12 -> 8265988 | BP3: 40 | BQ3: =M3*BP3 -> 3520 | BR3: =AZ3+31 -> 45628 | BS3: =FV(BY3,BK$1-1,0,-BQ3) -> 8841.7901 | BT3: =TIPOLOGÍAS!AZ3+(TIPOLOGÍAS!BK3*365.25) -> 51075.75 | BU3: =FV(BY3,BK$1,-BQ3*12,0) -> 1045240.9 | BW3: 23000 | BX3: =TIPOLOGÍAS!AZ3+62 -> 45659 | BY3: =BY$1 -> 0.068 | BZ3: =FV(BY3,BK$1,0,-BW3) -> 61701.628 | CA3: =TIPOLOGÍAS!AZ3+(TIPOLOGÍAS!BK3*365.25) -> 51075.75 | CB3: =CB$1 -> 11 | CC3: =FV(BY3,BK3,-BW3*CB3,0)-(2*BW3) -> 6214557.5 | CE3: =AV3+BF3+BN3+BU3 -> 10956951 | CF3: =CE3-CC3 -> 4742393.3 | CG3: =CF3/CL3 -> 28687.156 | CH3: =(RATE(CL3,-CG3,0,CO3))*12 -> 0.11600706 | CJ3: =CJ$1 -> 0.068 | CK3: =(AZ3-TODAY()+(BK$1*365.25)) -> 5031.75 | CL3: =CK3/30.4375 -> 165.31417 | CM3: =CL3/12 -> 13.776181 | CN3: =INT(CM3) & " años y " & INT((CM3-INT(CM3))*12) & " meses" -> 13 años y 9 meses | CO3: =FV(CJ3,((AZ3-TODAY())/365.25)+BK$1,0,-R3) -> 11590883
B4: 2 | C4: Si | D4: Monterrey | E4: Contry | F4: AISEN | G4: Novus | I4: A | J4: 14 | K4: Sur | M4: 79 | N4: 3740984 | O4: No | P4: =Q4/N4 -> 0 | R4: =IF(O4="No",N4,N4-Q4) -> 3740984 | S4: =R4/M4 -> 47354.228 | U4: Si | V4: Si | X4: 1 | Y4: No | Z4: 1.5 | AA4: Si | AB4: Si | AC4: Si | AD4: No | AF4: No | AH4: No | AI4: No | AJ4: 1 | AK4: No | AM4: No | AP4: 0.05 | AQ4: =N4*AP4 -> 187049.2 | AR4: 0.15 | AS4: =AR4*N4 -> 561147.6 | AT4: 18 | AU4: =AS4/AT4 -> 31174.867 | AV4: =AQ4+AS4 -> 748196.8 | AW4: =1-AP4-AR4 -> 0.8 | AX4: =N4-AQ4-(AT4*AU4) -> 2992787.2 | AZ4: 45261 | BB4: =N4*0.03 -> 112229.52 | BC4: =N4*0.02 -> 74819.68 | BD4: 180000 | BE4: 125000 | BF4: =BB4+BC4+BD4+BE4 -> 492049.2 | BH4: =AX4 -> 2992787.2 | BI4: =AZ4+31 -> 45292 | BJ4: =BJ$1 -> 0.12 | BK4: =BK$1 -> 15 | BL4: =PMT(BJ4/12,BK4*12,-AX4) -> 35918.476 | BM4: =TIPOLOGÍAS!AZ4+(TIPOLOGÍAS!BK4*365.25) -> 50739.75 | BN4: =BL4*BK4*12 -> 6465325.7 | BP4: 50 | BQ4: =M4*BP4 -> 3950 | BR4: =AZ4+31 -> 45292 | BS4: =FV(BY4,BK$1-1,0,-BQ4) -> 9921.8952 | BT4: =TIPOLOGÍAS!AZ4+(TIPOLOGÍAS!BK4*365.25) -> 50739.75 | BU4: =FV(BY4,BK$1,-BQ4*12,0) -> 1172926.6 | BW4: 18000 | BX4: =TIPOLOGÍAS!AZ4+62 -> 45323 | BY4: =BY$1 -> 0.068 | BZ4: =FV(BY4,BK$1,0,-BW4) -> 48288.231 | CA4: =TIPOLOGÍAS!AZ4+(TIPOLOGÍAS!BK4*365.25) -> 50739.75 | CB4: =CB$1 -> 11 | CC4: =FV(BY4,BK4,-BW4*CB4,0)-(2*BW4) -> 4863566.8 | CE4: =AV4+BF4+BN4+BU4 -> 8878498.3 | CF4: =CE4-CC4 -> 4014931.5 | CG4: =CF4/CL4 -> 26024.486 | CH4: =(RATE(CL4,-CG4,0,CO4))*12 -> 0.10929936 | CJ4: =CJ$1 -> 0.068 | CK4: =(AZ4-TODAY()+(BK$1*365.25)) -> 4695.75 | CL4: =CK4/30.4375 -> 154.27515 | CM4: =CL4/12 -> 12.856263 | CN4: =INT(CM4) & " años y " & INT((CM4-INT(CM4))*12) & " meses" -> 12 años y 10 meses | CO4: =FV(CJ4,((AZ4-TODAY())/365.25)+BK$1,0,-R4) -> 8715762.4
B5: 3 | C5: Si | D5: Monterrey | E5: Valle Oriente | F5: Altio | G5: Avalon | I5: X | J5: 7 | K5: Este | M5: 123 | N5: 4000000 | O5: No | P5: =Q5/N5 -> 0 | R5: =IF(O5="No",N5,N5-Q5) -> 4000000 | S5: =R5/M5 -> 32520.325 | U5: No | V5: No | X5: 3 | Y5: No | Z5: 2 | AA5: Si | AB5: Si | AC5: Si | AD5: Si | AE5: 5 | AF5: No | AH5: No | AI5: No | AJ5: 2 | AM5: No | AP5: 0.1 | AQ5: =N5*AP5 -> 400000 | AR5: 0.1 | AS5: =AR5*N5 -> 400000 | AT5: 30 | AU5: =AS5/AT5 -> 13333.333 | AV5: =AQ5+AS5 -> 800000 | AW5: =1-AP5-AR5 -> 0.8 | AX5: =N5-AQ5-(AT5*AU5) -> 3200000 | AZ5: 45748 | BB5: =N5*0.03 -> 120000 | BC5: =N5*0.02 -> 80000 | BD5: 150000 | BE5: 145000 | BF5: =BB5+BC5+BD5+BE5 -> 495000 | BH5: =AX5 -> 3200000 | BI5: =AZ5+31 -> 45779 | BJ5: =BJ$1 -> 0.12 | BK5: =BK$1 -> 15 | BL5: =PMT(BJ5/12,BK5*12,-AX5) -> 38405.378 | BM5: =TIPOLOGÍAS!AZ5+(TIPOLOGÍAS!BK5*365.25) -> 51226.75 | BN5: =BL5*BK5*12 -> 6912968 | BP5: 45 | BQ5: =M5*BP5 -> 5535 | BR5: =AZ5+31 -> 45779 | BS5: =FV(BY5,BK$1-1,0,-BQ5) -> 13903.213 | BT5: =TIPOLOGÍAS!AZ5+(TIPOLOGÍAS!BK5*365.25) -> 51226.75 | BU5: =FV(BY5,BK$1,-BQ5*12,0) -> 1643581.9 | BW5: 20000 | BX5: =TIPOLOGÍAS!AZ5+62 -> 45810 | BY5: =BY$1 -> 0.068 | BZ5: =FV(BY5,BK$1,0,-BW5) -> 53653.59 | CA5: =TIPOLOGÍAS!AZ5+(TIPOLOGÍAS!BK5*365.25) -> 51226.75 | CB5: =CB$1 -> 11 | CC5: =FV(BY5,BK5,-BW5*CB5,0)-(2*BW5) -> 5403963.1 | CE5: =AV5+BF5+BN5+BU5 -> 9851550 | CF5: =CE5-CC5 -> 4447586.9 | CG5: =CF5/CL5 -> 26119.999 | CH5: =(RATE(CL5,-CG5,0,CO5))*12 -> 0.10500172 | CJ5: =CJ$1 -> 0.068 | CK5: =(AZ5-TODAY()+(BK$1*365.25)) -> 5182.75 | CL5: =CK5/30.4375 -> 170.27515 | CM5: =CL5/12 -> 14.189596 | CN5: =INT(CM5) & " años y " & INT((CM5-INT(CM5))*12) & " meses" -> 14 años y 2 meses | CO5: =FV(CJ5,((AZ5-TODAY())/365.25)+BK$1,0,-R5) -> 10173597
B6: 4 | C6: Si | D6: Monterrey | E6: Sur | F6: Cuadro | G6: Arena Fundidora | I6: C | J6: 12 | K6: Oeste | M6: 65 | N6: 2987000 | O6: Si | P6: =Q6/N6 -> 0 | R6: =IF(O6="No",N6,N6-Q6) -> 2987000 | S6: =R6/M6 -> 45953.846 | U6: No | V6: No | X6: 2 | Y6: No | Z6: 2 | AA6: Si | AB6: Si | AC6: Si | AD6: Si | AE6: 6 | AF6: No | AH6: No | AI6: No | AJ6: 2 | AM6: No | AP6: 0.1 | AQ6: =N6*AP6 -> 298700 | AR6: 0.1 | AS6: =AR6*N6 -> 298700 | AT6: 24 | AU6: =AS6/AT6 -> 12445.833 | AV6: =AQ6+AS6 -> 597400 | AW6: =1-AP6-AR6 -> 0.8 | AX6: =N6-AQ6-(AT6*AU6) -> 2389600 | AZ6: 45627 | BB6: =N6*0.03 -> 89610 | BC6: =N6*0.02 -> 59740 | BD6: 220000 | BE6: 190000 | BF6: =BB6+BC6+BD6+BE6 -> 559350 | BH6: =AX6 -> 2389600 | BI6: =AZ6+31 -> 45658 | BJ6: =BJ$1 -> 0.12 | BK6: =BK$1 -> 15 | BL6: =PMT(BJ6/12,BK6*12,-AX6) -> 28679.216 | BM6: =TIPOLOGÍAS!AZ6+(TIPOLOGÍAS!BK6*365.25) -> 51105.75 | BN6: =BL6*BK6*12 -> 5162258.9 | BP6: 35 | BQ6: =M6*BP6 -> 2275 | BR6: =AZ6+31 -> 45658 | BS6: =FV(BY6,BK$1-1,0,-BQ6) -> 5714.5092 | BT6: =TIPOLOGÍAS!AZ6+(TIPOLOGÍAS!BK6*365.25) -> 51105.75 | BU6: =FV(BY6,BK$1,-BQ6*12,0) -> 675546.33 | BW6: 14000 | BX6: =TIPOLOGÍAS!AZ6+62 -> 45689 | BY6: =BY$1 -> 0.068 | BZ6: =FV(BY6,BK$1,0,-BW6) -> 37557.513 | CA6: =TIPOLOGÍAS!AZ6+(TIPOLOGÍAS!BK6*365.25) -> 51105.75 | CB6: =CB$1 -> 11 | CC6: =FV(BY6,BK6,-BW6*CB6,0)-(2*BW6) -> 3782774.2 | CE6: =AV6+BF6+BN6+BU6 -> 6994555.2 | CF6: =CE6-CC6 -> 3211781.1 | CG6: =CF6/CL6 -> 19313.199 | CH6: =(RATE(CL6,-CG6,0,CO6))*12 -> 0.10891793 | CJ6: =CJ$1 -> 0.068 | CK6: =(AZ6-TODAY()+(BK$1*365.25)) -> 5061.75 | CL6: =CK6/30.4375 -> 166.29979 | CM6: =CL6/12 -> 13.858316 | CN6: =INT(CM6) & " años y " & INT((CM6-INT(CM6))*12) & " meses" -> 13 años y 10 meses | CO6: =FV(CJ6,((AZ6-TODAY())/365.25)+BK$1,0,-R6) -> 7433351.6
B7: 5 | C7: Si | D7: Monterrey | E7: San José Tec | F7: AISEN | G7: Lívita 20 | I7: A | J7: 4 | K7: Obispado | M7: 88 | N7: 5477582 | O7: No | P7: =Q7/N7 -> 0 | R7: =IF(O7="No",N7,N7-Q7) -> 5477582 | S7: =R7/M7 -> 62245.25 | U7: No | V7: No | X7: 2 | Y7: No | Z7: 2 | AA7: Si | AB7: Si | AC7: Si | AD7: Si | AE7: 3 | AF7: No | AH7: Si | AI7: No | AJ7: 2 | AM7: Si | AP7: 0.15 | AQ7: =N7*AP7 -> 821637.3 | AR7: 0.15 | AS7: =AR7*N7 -> 821637.3 | AT7: 21 | AU7: =AS7/AT7 -> 39125.586 | AV7: =AQ7+AS7 -> 1643274.6 | AW7: =1-AP7-AR7 -> 0.7 | AX7: =N7-AQ7-(AT7*AU7) -> 3834307.4 | AZ7: 45931 | BB7: =N7*0.03 -> 164327.46 | BC7: =N7*0.02 -> 109551.64 | BD7: 290000 | BE7: 200000 | BF7: =BB7+BC7+BD7+BE7 -> 763879.1 | BH7: =AX7 -> 3834307.4 | BI7: =AZ7+31 -> 45962 | BJ7: =BJ$1 -> 0.12 | BK7: =BK$1 -> 15 | BL7: =PMT(BJ7/12,BK7*12,-AX7) -> 46018.133 | BM7: =TIPOLOGÍAS!AZ7+(TIPOLOGÍAS!BK7*365.25) -> 51409.75 | BN7: =BL7*BK7*12 -> 8283263.9 | BP7: 45 | BQ7: =M7*BP7 -> 3960 | BR7: =AZ7+31 -> 45962 | BS7: =FV(BY7,BK$1-1,0,-BQ7) -> 9947.0139 | BT7: =TIPOLOGÍAS!AZ7+(TIPOLOGÍAS!BK7*365.25) -> 51409.75 | BU7: =FV(BY7,BK$1,-BQ7*12,0) -> 1175896 | BW7: 28800 | BX7: =TIPOLOGÍAS!AZ7+62 -> 45993 | BY7: =BY$1 -> 0.068 | BZ7: =FV(BY7,BK$1,0,-BW7) -> 77261.17 | CA7: =TIPOLOGÍAS!AZ7+(TIPOLOGÍAS!BK7*365.25) -> 51409.75 | CB7: =CB$1 -> 11 | CC7: =FV(BY7,BK7,-BW7*CB7,0)-(2*BW7) -> 7781706.8 | CE7: =AV7+BF7+BN7+BU7 -> 11866314 | CF7: =CE7-CC7 -> 4084606.8 | CG7: =CF7/CL7 -> 23170.148 | CH7: =(RATE(CL7,-CG7,0,CO7))*12 -> 0.14779984 | CJ7: =CJ$1 -> 0.068 | CK7: =(AZ7-TODAY()+(BK$1*365.25)) -> 5365.75 | CL7: =CK7/30.4375 -> 176.28747 | CM7: =CL7/12 -> 14.690623 | CN7: =INT(CM7) & " años y " & INT((CM7-INT(CM7))*12) & " meses" -> 14 años y 8 meses | CO7: =FV(CJ7,((AZ7-TODAY())/365.25)+BK$1,0,-R7) -> 14398538
B8: 6 | C8: Si | D8: Monterrey | E8: Maria Luisa | F8: Quantium | G8: Moca Azul | I8: A | J8: 20 | K8: Sur | M8: 123 | N8: 3660665 | O8: No | P8: =Q8/N8 -> 0 | R8: =IF(O8="No",N8,N8-Q8) -> 3660665 | S8: =R8/M8 -> 29761.504 | U8: No | X8: 2.5 | Y8: No | Z8: 1 | AA8: Si | AB8: Si | AC8: Si | AD8: No | AF8: No | AH8: No | AI8: No | AJ8: 2 | AM8: No | AP8: 0.1 | AQ8: =N8*AP8 -> 366066.5 | AR8: 0.1 | AS8: =AR8*N8 -> 366066.5 | AT8: 26 | AU8: =AS8/AT8 -> 14079.481 | AV8: =AQ8+AS8 -> 732133 | AW8: =1-AP8-AR8 -> 0.8 | AX8: =N8-AQ8-(AT8*AU8) -> 2928532 | AZ8: 45261 | BB8: =N8*0.03 -> 109819.95 | BC8: =N8*0.02 -> 73213.3 | BD8: 255000 | BE8: 172500 | BF8: =BB8+BC8+BD8+BE8 -> 610533.25 | BH8: =AX8 -> 2928532 | BI8: =AZ8+31 -> 45292 | BJ8: =BJ$1 -> 0.12 | BK8: =BK$1 -> 15 | BL8: =PMT(BJ8/12,BK8*12,-AX8) -> 35147.306 | BM8: =TIPOLOGÍAS!AZ8+(TIPOLOGÍAS!BK8*365.25) -> 50739.75 | BN8: =BL8*BK8*12 -> 6326515 | BP8: 42.5 | BQ8: =M8*BP8 -> 5227.5 | BR8: =AZ8+31 -> 45292 | BS8: =FV(BY8,BK$1-1,0,-BQ8) -> 13130.812 | BT8: =TIPOLOGÍAS!AZ8+(TIPOLOGÍAS!BK8*365.25) -> 50739.75 | BU8: =FV(BY8,BK$1,-BQ8*12,0) -> 1552271.8 | BW8: 15800 | BX8: =TIPOLOGÍAS!AZ8+62 -> 45323 | BY8: =BY$1 -> 0.068 | BZ8: =FV(BY8,BK$1,0,-BW8) -> 42386.336 | CA8: =TIPOLOGÍAS!AZ8+(TIPOLOGÍAS!BK8*365.25) -> 50739.75 | CB8: =CB$1 -> 11 | CC8: =FV(BY8,BK8,-BW8*CB8,0)-(2*BW8) -> 4269130.8 | CE8: =AV8+BF8+BN8+BU8 -> 9221453.1 | CF8: =CE8-CC8 -> 4952322.3 | CG8: =CF8/CL8 -> 32100.582 | CH8: =(RATE(CL8,-CG8,0,CO8))*12 -> 0.078778023 | CJ8: =CJ$1 -> 0.068 | CK8: =(AZ8-TODAY()+(BK$1*365.25)) -> 4695.75 | CL8: =CK8/30.4375 -> 154.27515 | CM8: =CL8/12 -> 12.856263 | CN8: =INT(CM8) & " años y " & INT((CM8-INT(CM8))*12) & " meses" -> 12 años y 10 meses | CO8: =FV(CJ8,((AZ8-TODAY())/365.25)+BK$1,0,-R8) -> 8528634.9
B9: 7 | C9: Si | D9: Monterrey | E9: Cumbres | F9: AISEN | G9: Moca Verde | I9: X | J9: 8 | K9: Este | M9: 88.62 | N9: 3590664 | O9: No | P9: =Q9/N9 -> 0 | R9: =IF(O9="No",N9,N9-Q9) -> 3590664 | S9: =R9/M9 -> 40517.536 | U9: No | V9: No | X9: 2.7 | Y9: No | Z9: 2 | AA9: Si | AB9: Si | AC9: Si | AD9: Si | AE9: 5 | AF9: No | AH9: No | AI9: No | AJ9: 1 | AM9: No | AP9: 0.05 | AQ9: =N9*AP9 -> 179533.2 | AR9: 0.05 | AS9: =AR9*N9 -> 179533.2 | AT9: 21 | AU9: =AS9/AT9 -> 8549.2 | AV9: =AQ9+AS9 -> 359066.4 | AW9: =1-AP9-AR9 -> 0.9 | AX9: =N9-AQ9-(AT9*AU9) -> 3231597.6 | AZ9: 45748 | BB9: =N9*0.03 -> 107719.92 | BC9: =N9*0.02 -> 71813.28 | BD9: 278500 | BE9: 181500 | BF9: =BB9+BC9+BD9+BE9 -> 639533.2 | BH9: =AX9 -> 3231597.6 | BI9: =AZ9+31 -> 45779 | BJ9: =BJ$1 -> 0.12 | BK9: =BK$1 -> 15 | BL9: =PMT(BJ9/12,BK9*12,-AX9) -> 38784.602 | BM9: =TIPOLOGÍAS!AZ9+(TIPOLOGÍAS!BK9*365.25) -> 51226.75 | BN9: =BL9*BK9*12 -> 6981228.4 | BP9: 41.5 | BQ9: =M9*BP9 -> 3677.73 | BR9: =AZ9+31 -> 45779 | BS9: =FV(BY9,BK$1-1,0,-BQ9) -> 9237.9877 | BT9: =TIPOLOGÍAS!AZ9+(TIPOLOGÍAS!BK9*365.25) -> 51226.75 | BU9: =FV(BY9,BK$1,-BQ9*12,0) -> 1092077.8 | BW9: 15140 | BX9: =TIPOLOGÍAS!AZ9+62 -> 45810 | BY9: =BY$1 -> 0.068 | BZ9: =FV(BY9,BK$1,0,-BW9) -> 40615.768 | CA9: =TIPOLOGÍAS!AZ9+(TIPOLOGÍAS!BK9*365.25) -> 51226.75 | CB9: =CB$1 -> 11 | CC9: =FV(BY9,BK9,-BW9*CB9,0)-(2*BW9) -> 4090800.1 | CE9: =AV9+BF9+BN9+BU9 -> 9071905.8 | CF9: =CE9-CC9 -> 4981105.8 | CG9: =CF9/CL9 -> 29253.274 | CH9: =(RATE(CL9,-CG9,0,CO9))*12 -> 0.078919503 | CJ9: =CJ$1 -> 0.068 | CK9: =(AZ9-TODAY()+(BK$1*365.25)) -> 5182.75 | CL9: =CK9/30.4375 -> 170.27515 | CM9: =CL9/12 -> 14.189596 | CN9: =INT(CM9) & " años y " & INT((CM9-INT(CM9))*12) & " meses" -> 14 años y 2 meses | CO9: =FV(CJ9,((AZ9-TODAY())/365.25)+BK$1,0,-R9) -> 9132492.1
B10: 8 | C10: Si | D10: Monterrey | E10: Contry | F10: Altio | G10: Colonia | I10: C | J10: 14 | K10: Oeste | M10: 88.04 | N10: 3520663 | O10: No | P10: =Q10/N10 -> 0 | R10: =IF(O10="No",N10,N10-Q10) -> 3520663 | S10: =R10/M10 -> 39989.357 | U10: No | V10: No | X10: 2.9 | Y10: No | Z10: 1 | AA10: Si | AB10: Si | AC10: Si | AD10: Si | AE10: 6 | AF10: No | AH10: No | AI10: No | AJ10: 2 | AM10: No | AP10: 0.1 | AQ10: =N10*AP10 -> 352066.3 | AR10: 0.1 | AS10: =AR10*N10 -> 352066.3 | AT10: 18 | AU10: =AS10/AT10 -> 19559.239 | AV10: =AQ10+AS10 -> 704132.6 | AW10: =1-AP10-AR10 -> 0.8 | AX10: =N10-AQ10-(AT10*AU10) -> 2816530.4 | AZ10: 45627 | BB10: =N10*0.03 -> 105619.89 | BC10: =N10*0.02 -> 70413.26 | BD10: 302000 | BE10: 190500 | BF10: =BB10+BC10+BD10+BE10 -> 668533.15 | BH10: =AX10 -> 2816530.4 | BI10: =AZ10+31 -> 45658 | BJ10: =BJ$1 -> 0.12 | BK10: =BK$1 -> 15 | BL10: =PMT(BJ10/12,BK10*12,-AX10) -> 33803.098 | BM10: =TIPOLOGÍAS!AZ10+(TIPOLOGÍAS!BK10*365.25) -> 51105.75 | BN10: =BL10*BK10*12 -> 6084557.7 | BP10: 40.5 | BQ10: =M10*BP10 -> 3565.62 | BR10: =AZ10+31 -> 45658 | BS10: =FV(BY10,BK$1-1,0,-BQ10) -> 8956.3817 | BT10: =TIPOLOGÍAS!AZ10+(TIPOLOGÍAS!BK10*365.25) -> 51105.75 | BU10: =FV(BY10,BK$1,-BQ10*12,0) -> 1058787.5 | BW10: 14480 | BX10: =TIPOLOGÍAS!AZ10+62 -> 45689 | BY10: =BY$1 -> 0.068 | BZ10: =FV(BY10,BK$1,0,-BW10) -> 38845.199 | CA10: =TIPOLOGÍAS!AZ10+(TIPOLOGÍAS!BK10*365.25) -> 51105.75 | CB10: =CB$1 -> 11 | CC10: =FV(BY10,BK10,-BW10*CB10,0)-(2*BW10) -> 3912469.3 | CE10: =AV10+BF10+BN10+BU10 -> 8516010.9 | CF10: =CE10-CC10 -> 4603541.6 | CG10: =CF10/CL10 -> 27682.185 | CH10: =(RATE(CL10,-CG10,0,CO10))*12 -> 0.085416246 | CJ10: =CJ$1 -> 0.068 | CK10: =(AZ10-TODAY()+(BK$1*365.25)) -> 5061.75 | CL10: =CK10/30.4375 -> 166.29979 | CM10: =CL10/12 -> 13.858316 | CN10: =INT(CM10) & " años y " & INT((CM10-INT(CM10))*12) & " meses" -> 13 años y 10 meses | CO10: =FV(CJ10,((AZ10-TODAY())/365.25)+BK$1,0,-R10) -> 8761408.1
B11: 9 | C11: Si | D11: Monterrey | E11: Valle Oriente | F11: Cuadro | G11: Lívita 20 | I11: B | J11: 7 | K11: Sur | M11: 45 | N11: 3450662 | O11: No | P11: =Q11/N11 -> 0 | R11: =IF(O11="No",N11,N11-Q11) -> 3450662 | S11: =R11/M11 -> 76681.378 | U11: No | V11: No | X11: 3.1 | Y11: No | Z11: 1 | AA11: Si | AB11: Si | AC11: Si | AD11: No | AF11: No | AH11: No | AI11: No | AJ11: 2 | AM11: No | AP11: 0.1 | AQ11: =N11*AP11 -> 345066.2 | AR11: 0.1 | AS11: =AR11*N11 -> 345066.2 | AT11: 30 | AU11: =AS11/AT11 -> 11502.207 | AV11: =AQ11+AS11 -> 690132.4 | AW11: =1-AP11-AR11 -> 0.8 | AX11: =N11-AQ11-(AT11*AU11) -> 2760529.6 | AZ11: 45597 | BB11: =N11*0.03 -> 103519.86 | BC11: =N11*0.02 -> 69013.24 | BD11: 325500 | BE11: 199500 | BF11: =BB11+BC11+BD11+BE11 -> 697533.1 | BH11: =AX11 -> 2760529.6 | BI11: =AZ11+31 -> 45628 | BJ11: =BJ$1 -> 0.12 | BK11: =BK$1 -> 15 | BL11: =PMT(BJ11/12,BK11*12,-AX11) -> 33130.995 | BM11: =TIPOLOGÍAS!AZ11+(TIPOLOGÍAS!BK11*365.25) -> 51075.75 | BN11: =BL11*BK11*12 -> 5963579 | BP11: 39.5 | BQ11: =M11*BP11 -> 1777.5 | BR11: =AZ11+31 -> 45628 | BS11: =FV(BY11,BK$1-1,0,-BQ11) -> 4464.8528 | BT11: =TIPOLOGÍAS!AZ11+(TIPOLOGÍAS!BK11*365.25) -> 51075.75 | BU11: =FV(BY11,BK$1,-BQ11*12,0) -> 527816.97 | BW11: 13820 | BX11: =TIPOLOGÍAS!AZ11+62 -> 45659 | BY11: =BY$1 -> 0.068 | BZ11: =FV(BY11,BK$1,0,-BW11) -> 37074.631 | CA11: =TIPOLOGÍAS!AZ11+(TIPOLOGÍAS!BK11*365.25) -> 51075.75 | CB11: =CB$1 -> 11 | CC11: =FV(BY11,BK11,-BW11*CB11,0)-(2*BW11) -> 3734138.5 | CE11: =AV11+BF11+BN11+BU11 -> 7879061.5 | CF11: =CE11-CC11 -> 4144923 | CG11: =CF11/CL11 -> 25073.005 | CH11: =(RATE(CL11,-CG11,0,CO11))*12 -> 0.09564432 | CJ11: =CJ$1 -> 0.068 | CK11: =(AZ11-TODAY()+(BK$1*365.25)) -> 5031.75 | CL11: =CK11/30.4375 -> 165.31417 | CM11: =CL11/12 -> 13.776181 | CN11: =INT(CM11) & " años y " & INT((CM11-INT(CM11))*12) & " meses" -> 13 años y 9 meses | CO11: =FV(CJ11,((AZ11-TODAY())/365.25)+BK$1,0,-R11) -> 8540930
B12: 10 | C12: Si | D12: Monterrey | E12: Sur | F12: Creare | G12: Novus | I12: A | J12: 12 | K12: Sur | M12: 86.88 | N12: 3380661 | O12: No | P12: =Q12/N12 -> 0 | R12: =IF(O12="No",N12,N12-Q12) -> 3380661 | S12: =R12/M12 -> 38911.844 | U12: No | V12: No | X12: 3.3 | Y12: No | Z12: 2 | AA12: Si | AB12: Si | AC12: Si | AD12: No | AF12: No | AH12: No | AI12: No | AJ12: 2 | AM12: No | AP12: 0.1 | AQ12: =N12*AP12 -> 338066.1 | AR12: 0.1 | AS12: =AR12*N12 -> 338066.1 | AT12: 24 | AU12: =AS12/AT12 -> 14086.088 | AV12: =AQ12+AS12 -> 676132.2 | AW12: =1-AP12-AR12 -> 0.8 | AX12: =N12-AQ12-(AT12*AU12) -> 2704528.8 | AZ12: 45261 | BB12: =N12*0.03 -> 101419.83 | BC12: =N12*0.02 -> 67613.22 | BD12: 349000 | BE12: 208500 | BF12: =BB12+BC12+BD12+BE12 -> 726533.05 | BH12: =AX12 -> 2704528.8 | BI12: =AZ12+31 -> 45292 | BJ12: =BJ$1 -> 0.12 | BK12: =BK$1 -> 15 | BL12: =PMT(BJ12/12,BK12*12,-AX12) -> 32458.891 | BM12: =TIPOLOGÍAS!AZ12+(TIPOLOGÍAS!BK12*365.25) -> 50739.75 | BN12: =BL12*BK12*12 -> 5842600.4 | BP12: 38.5 | BQ12: =M12*BP12 -> 3344.88 | BR12: =AZ12+31 -> 45292 | BS12: =FV(BY12,BK$1-1,0,-BQ12) -> 8401.9111 | BT12: =TIPOLOGÍAS!AZ12+(TIPOLOGÍAS!BK12*365.25) -> 50739.75 | BU12: =FV(BY12,BK$1,-BQ12*12,0) -> 993240.18 | BW12: 13160 | BX12: =TIPOLOGÍAS!AZ12+62 -> 45323 | BY12: =BY$1 -> 0.068 | BZ12: =FV(BY12,BK$1,0,-BW12) -> 35304.062 | CA12: =TIPOLOGÍAS!AZ12+(TIPOLOGÍAS!BK12*365.25) -> 50739.75 | CB12: =CB$1 -> 11 | CC12: =FV(BY12,BK12,-BW12*CB12,0)-(2*BW12) -> 3555807.7 | CE12: =AV12+BF12+BN12+BU12 -> 8238505.8 | CF12: =CE12-CC12 -> 4682698.1 | CG12: =CF12/CL12 -> 30352.898 | CH12: =(RATE(CL12,-CG12,0,CO12))*12 -> 0.075582089 | CJ12: =CJ$1 -> 0.068 | CK12: =(AZ12-TODAY()+(BK$1*365.25)) -> 4695.75 | CL12: =CK12/30.4375 -> 154.27515 | CM12: =CL12/12 -> 12.856263 | CN12: =INT(CM12) & " años y " & INT((CM12-INT(CM12))*12) & " meses" -> 12 años y 10 meses | CO12: =FV(CJ12,((AZ12-TODAY())/365.25)+BK$1,0,-R12) -> 7876280.2
B13: 11 | C13: Si | D13: Monterrey | E13: Galerías | F13: Quantium | G13: Avalon | I13: X | J13: 21 | K13: Este | M13: 86.3 | N13: 3310660 | O13: No | P13: =Q13/N13 -> 0 | R13: =IF(O13="No",N13,N13-Q13) -> 3310660 | S13: =R13/M13 -> 38362.225 | U13: No | V13: No | X13: 3.5 | Y13: No | Z13: 1.5 | AA13: Si | AB13: Si | AC13: Si | AD13: Si | AE13: 6 | AF13: No | AH13: No | AI13: No | AJ13: 2 | AM13: No | AP13: 0.1 | AQ13: =N13*AP13 -> 331066 | AR13: 0.1 | AS13: =AR13*N13 -> 331066 | AT13: 23 | AU13: =AS13/AT13 -> 14394.174 | AV13: =AQ13+AS13 -> 662132 | AW13: =1-AP13-AR13 -> 0.8 | AX13: =N13-AQ13-(AT13*AU13) -> 2648528 | AZ13: 45748 | BB13: =N13*0.03 -> 99319.8 | BC13: =N13*0.02 -> 66213.2 | BD13: 235000 | BE13: 217500 | BF13: =BB13+BC13+BD13+BE13 -> 618033 | BH13: =AX13 -> 2648528 | BI13: =AZ13+31 -> 45779 | BJ13: =BJ$1 -> 0.12 | BK13: =BK$1 -> 15 | BL13: =PMT(BJ13/12,BK13*12,-AX13) -> 31786.787 | BM13: =TIPOLOGÍAS!AZ13+(TIPOLOGÍAS!BK13*365.25) -> 51226.75 | BN13: =BL13*BK13*12 -> 5721621.7 | BP13: 37.5 | BQ13: =M13*BP13 -> 3236.25 | BR13: =AZ13+31 -> 45779 | BS13: =FV(BY13,BK$1-1,0,-BQ13) -> 8129.0464 | BT13: =TIPOLOGÍAS!AZ13+(TIPOLOGÍAS!BK13*365.25) -> 51226.75 | BU13: =FV(BY13,BK$1,-BQ13*12,0) -> 960983.21 | BW13: 12500 | BX13: =TIPOLOGÍAS!AZ13+62 -> 45810 | BY13: =BY$1 -> 0.068 | BZ13: =FV(BY13,BK$1,0,-BW13) -> 33533.494 | CA13: =TIPOLOGÍAS!AZ13+(TIPOLOGÍAS!BK13*365.25) -> 51226.75 | CB13: =CB$1 -> 11 | CC13: =FV(BY13,BK13,-BW13*CB13,0)-(2*BW13) -> 3377476.9 | CE13: =AV13+BF13+BN13+BU13 -> 7962769.9 | CF13: =CE13-CC13 -> 4585293 | CG13: =CF13/CL13 -> 26928.726 | CH13: =(RATE(CL13,-CG13,0,CO13))*12 -> 0.079113436 | CJ13: =CJ$1 -> 0.068 | CK13: =(AZ13-TODAY()+(BK$1*365.25)) -> 5182.75 | CL13: =CK13/30.4375 -> 170.27515 | CM13: =CL13/12 -> 14.189596 | CN13: =INT(CM13) & " años y " & INT((CM13-INT(CM13))*12) & " meses" -> 14 años y 2 meses | CO13: =FV(CJ13,((AZ13-TODAY())/365.25)+BK$1,0,-R13) -> 8420330.1
B14: 12 | C14: Si | D14: Monterrey | E14: Maria Luisa | F14: AISEN | G14: Arena Fundidora | I14: C | J14: 20 | K14: Oeste | M14: 67 | N14: 3240659 | O14: No | P14: =Q14/N14 -> 0 | R14: =IF(O14="No",N14,N14-Q14) -> 3240659 | S14: =R14/M14 -> 48368.045 | U14: No | V14: No | X14: 3.7 | Y14: No | Z14: 2 | AA14: Si | AB14: Si | AC14: Si | AD14: Si | AE14: 7 | AF14: No | AH14: No | AI14: No | AJ14: 1 | AM14: No | AP14: 0.05 | AQ14: =N14*AP14 -> 162032.95 | AR14: 0.05 | AS14: =AR14*N14 -> 162032.95 | AT14: 26 | AU14: =AS14/AT14 -> 6232.0365 | AV14: =AQ14+AS14 -> 324065.9 | AW14: =1-AP14-AR14 -> 0.9 | AX14: =N14-AQ14-(AT14*AU14) -> 2916593.1 | AZ14: 45627 | BB14: =N14*0.03 -> 97219.77 | BC14: =N14*0.02 -> 64813.18 | BD14: 255000 | BE14: 226500 | BF14: =BB14+BC14+BD14+BE14 -> 643532.95 | BH14: =AX14 -> 2916593.1 | BI14: =AZ14+31 -> 45658 | BJ14: =BJ$1 -> 0.12 | BK14: =BK$1 -> 15 | BL14: =PMT(BJ14/12,BK14*12,-AX14) -> 35004.019 | BM14: =TIPOLOGÍAS!AZ14+(TIPOLOGÍAS!BK14*365.25) -> 51105.75 | BN14: =BL14*BK14*12 -> 6300723.4 | BP14: 36.5 | BQ14: =M14*BP14 -> 2445.5 | BR14: =AZ14+31 -> 45658 | BS14: =FV(BY14,BK$1-1,0,-BQ14) -> 6142.7834 | BT14: =TIPOLOGÍAS!AZ14+(TIPOLOGÍAS!BK14*365.25) -> 51105.75 | BU14: =FV(BY14,BK$1,-BQ14*12,0) -> 726175.18 | BW14: 11840 | BX14: =TIPOLOGÍAS!AZ14+62 -> 45689 | BY14: =BY$1 -> 0.068 | BZ14: =FV(BY14,BK$1,0,-BW14) -> 31762.925 | CA14: =TIPOLOGÍAS!AZ14+(TIPOLOGÍAS!BK14*365.25) -> 51105.75 | CB14: =CB$1 -> 11 | CC14: =FV(BY14,BK14,-BW14*CB14,0)-(2*BW14) -> 3199146.1 | CE14: =AV14+BF14+BN14+BU14 -> 7994497.4 | CF14: =CE14-CC14 -> 4795351.3 | CG14: =CF14/CL14 -> 28835.582 | CH14: =(RATE(CL14,-CG14,0,CO14))*12 -> 0.070054274 | CJ14: =CJ$1 -> 0.068 | CK14: =(AZ14-TODAY()+(BK$1*365.25)) -> 5061.75 | CL14: =CK14/30.4375 -> 166.29979 | CM14: =CL14/12 -> 13.858316 | CN14: =INT(CM14) & " años y " & INT((CM14-INT(CM14))*12) & " meses" -> 13 años y 10 meses | CO14: =FV(CJ14,((AZ14-TODAY())/365.25)+BK$1,0,-R14) -> 8064599.2
B15: 13 | C15: Si | D15: Monterrey | E15: Cumbres | F15: Altio | G15: Arena Calzada | I15: B | J15: 8 | K15: Sur | M15: 85.14 | N15: 3170658 | O15: No | P15: =Q15/N15 -> 0 | R15: =IF(O15="No",N15,N15-Q15) -> 3170658 | S15: =R15/M15 -> 37240.521 | U15: No | V15: No | X15: 3.9 | Y15: No | Z15: 2 | AA15: Si | AB15: Si | AC15: Si | AD15: Si | AE15: 7 | AF15: No | AH15: No | AI15: No | AJ15: 2 | AM15: No | AP15: 0.1 | AQ15: =N15*AP15 -> 317065.8 | AR15: 0.1 | AS15: =AR15*N15 -> 317065.8 | AT15: 21 | AU15: =AS15/AT15 -> 15098.371 | AV15: =AQ15+AS15 -> 634131.6 | AW15: =1-AP15-AR15 -> 0.8 | AX15: =N15-AQ15-(AT15*AU15) -> 2536526.4 | AZ15: 45597 | BB15: =N15*0.03 -> 95119.74 | BC15: =N15*0.02 -> 63413.16 | BD15: 278500 | BE15: 235500 | BF15: =BB15+BC15+BD15+BE15 -> 672532.9 | BH15: =AX15 -> 2536526.4 | BI15: =AZ15+31 -> 45628 | BJ15: =BJ$1 -> 0.12 | BK15: =BK$1 -> 15 | BL15: =PMT(BJ15/12,BK15*12,-AX15) -> 30442.58 | BM15: =TIPOLOGÍAS!AZ15+(TIPOLOGÍAS!BK15*365.25) -> 51075.75 | BN15: =BL15*BK15*12 -> 5479664.4 | BP15: 35.5 | BQ15: =M15*BP15 -> 3022.47 | BR15: =AZ15+31 -> 45628 | BS15: =FV(BY15,BK$1-1,0,-BQ15) -> 7592.0583 | BT15: =TIPOLOGÍAS!AZ15+(TIPOLOGÍAS!BK15*365.25) -> 51075.75 | BU15: =FV(BY15,BK$1,-BQ15*12,0) -> 897502.64 | BW15: 11180 | BX15: =TIPOLOGÍAS!AZ15+62 -> 45659 | BY15: =BY$1 -> 0.068 | BZ15: =FV(BY15,BK$1,0,-BW15) -> 29992.357 | CA15: =TIPOLOGÍAS!AZ15+(TIPOLOGÍAS!BK15*365.25) -> 51075.75 | CB15: =CB$1 -> 11 | CC15: =FV(BY15,BK15,-BW15*CB15,0)-(2*BW15) -> 3020815.4 | CE15: =AV15+BF15+BN15+BU15 -> 7683831.5 | CF15: =CE15-CC15 -> 4663016.1 | CG15: =CF15/CL15 -> 28206.996 | CH15: =(RATE(CL15,-CG15,0,CO15))*12 -> 0.070569534 | CJ15: =CJ$1 -> 0.068 | CK15: =(AZ15-TODAY()+(BK$1*365.25)) -> 5031.75 | CL15: =CK15/30.4375 -> 165.31417 | CM15: =CL15/12 -> 13.776181 | CN15: =INT(CM15) & " años y " & INT((CM15-INT(CM15))*12) & " meses" -> 13 años y 9 meses | CO15: =FV(CJ15,((AZ15-TODAY())/365.25)+BK$1,0,-R15) -> 7847876.1
B16: 14 | C16: Si | D16: Monterrey | E16: Contry | F16: Cuadro | G16: Moca Azul | I16: A | J16: 14 | K16: Sur | M16: 84.56 | N16: 3100657 | O16: No | P16: =Q16/N16 -> 0 | R16: =IF(O16="No",N16,N16-Q16) -> 3100657 | S16: =R16/M16 -> 36668.129 | U16: No | V16: No | X16: 4.1 | Y16: No | Z16: 2 | AA16: Si | AB16: Si | AC16: Si | AD16: Si | AE16: 6 | AF16: No | AH16: No | AI16: No | AJ16: 2 | AM16: No | AP16: 0.1 | AQ16: =N16*AP16 -> 310065.7 | AR16: 0.1 | AS16: =AR16*N16 -> 310065.7 | AT16: 18 | AU16: =AS16/AT16 -> 17225.872 | AV16: =AQ16+AS16 -> 620131.4 | AW16: =1-AP16-AR16 -> 0.8 | AX16: =N16-AQ16-(AT16*AU16) -> 2480525.6 | AZ16: 45261 | BB16: =N16*0.03 -> 93019.71 | BC16: =N16*0.02 -> 62013.14 | BD16: 302000 | BE16: 172500 | BF16: =BB16+BC16+BD16+BE16 -> 629532.85 | BH16: =AX16 -> 2480525.6 | BI16: =AZ16+31 -> 45292 | BJ16: =BJ$1 -> 0.12 | BK16: =BK$1 -> 15 | BL16: =PMT(BJ16/12,BK16*12,-AX16) -> 29770.476 | BM16: =TIPOLOGÍAS!AZ16+(TIPOLOGÍAS!BK16*365.25) -> 50739.75 | BN16: =BL16*BK16*12 -> 5358685.7 | BP16: 34.5 | BQ16: =M16*BP16 -> 2917.32 | BR16: =AZ16+31 -> 45292 | BS16: =FV(BY16,BK$1-1,0,-BQ16) -> 7327.935 | BT16: =TIPOLOGÍAS!AZ16+(TIPOLOGÍAS!BK16*365.25) -> 50739.75 | BU16: =FV(BY16,BK$1,-BQ16*12,0) -> 866279.04 | BW16: 10520 | BX16: =TIPOLOGÍAS!AZ16+62 -> 45323 | BY16: =BY$1 -> 0.068 | BZ16: =FV(BY16,BK$1,0,-BW16) -> 28221.788 | CA16: =TIPOLOGÍAS!AZ16+(TIPOLOGÍAS!BK16*365.25) -> 50739.75 | CB16: =CB$1 -> 11 | CC16: =FV(BY16,BK16,-BW16*CB16,0)-(2*BW16) -> 2842484.6 | CE16: =AV16+BF16+BN16+BU16 -> 7474629 | CF16: =CE16-CC16 -> 4632144.4 | CG16: =CF16/CL16 -> 30025.213 | CH16: =(RATE(CL16,-CG16,0,CO16))*12 -> 0.065222029 | CJ16: =CJ$1 -> 0.068 | CK16: =(AZ16-TODAY()+(BK$1*365.25)) -> 4695.75 | CL16: =CK16/30.4375 -> 154.27515 | CM16: =CL16/12 -> 12.856263 | CN16: =INT(CM16) & " años y " & INT((CM16-INT(CM16))*12) & " meses" -> 12 años y 10 meses | CO16: =FV(CJ16,((AZ16-TODAY())/365.25)+BK$1,0,-R16) -> 7223925.5
B17: 15 | C17: Si | D17: Monterrey | E17: Valle Oriente | F17: Creare | G17: Moca Verde | I17: X | J17: 7 | K17: Este | M17: 89 | N17: 3030656 | O17: No | P17: =Q17/N17 -> 0 | R17: =IF(O17="No",N17,N17-Q17) -> 3030656 | S17: =R17/M17 -> 34052.315 | U17: No | V17: No | X17: 4.3 | Y17: No | Z17: 1 | AA17: Si | AB17: Si | AC17: Si | AD17: Si | AE17: 5 | AF17: No | AH17: No | AI17: No | AJ17: 2 | AM17: No | AP17: 0.1 | AQ17: =N17*AP17 -> 303065.6 | AR17: 0.1 | AS17: =AR17*N17 -> 303065.6 | AT17: 30 | AU17: =AS17/AT17 -> 10102.187 | AV17: =AQ17+AS17 -> 606131.2 | AW17: =1-AP17-AR17 -> 0.8 | AX17: =N17-AQ17-(AT17*AU17) -> 2424524.8 | AZ17: 45748 | BB17: =N17*0.03 -> 90919.68 | BC17: =N17*0.02 -> 60613.12 | BD17: 325500 | BE17: 181500 | BF17: =BB17+BC17+BD17+BE17 -> 658532.8 | BH17: =AX17 -> 2424524.8 | BI17: =AZ17+31 -> 45779 | BJ17: =BJ$1 -> 0.12 | BK17: =BK$1 -> 15 | BL17: =PMT(BJ17/12,BK17*12,-AX17) -> 29098.372 | BM17: =TIPOLOGÍAS!AZ17+(TIPOLOGÍAS!BK17*365.25) -> 51226.75 | BN17: =BL17*BK17*12 -> 5237707 | BP17: 33.5 | BQ17: =M17*BP17 -> 2981.5 | BR17: =AZ17+31 -> 45779 | BS17: =FV(BY17,BK$1-1,0,-BQ17) -> 7489.1469 | BT17: =TIPOLOGÍAS!AZ17+(TIPOLOGÍAS!BK17*365.25) -> 51226.75 | BU17: =FV(BY17,BK$1,-BQ17*12,0) -> 885336.87 | BW17: 9860 | BX17: =TIPOLOGÍAS!AZ17+62 -> 45810 | BY17: =BY$1 -> 0.068 | BZ17: =FV(BY17,BK$1,0,-BW17) -> 26451.22 | CA17: =TIPOLOGÍAS!AZ17+(TIPOLOGÍAS!BK17*365.25) -> 51226.75 | CB17: =CB$1 -> 11 | CC17: =FV(BY17,BK17,-BW17*CB17,0)-(2*BW17) -> 2664153.8 | CE17: =AV17+BF17+BN17+BU17 -> 7387707.9 | CF17: =CE17-CC17 -> 4723554.1 | CG17: =CF17/CL17 -> 27740.712 | CH17: =(RATE(CL17,-CG17,0,CO17))*12 -> 0.064689985 | CJ17: =CJ$1 -> 0.068 | CK17: =(AZ17-TODAY()+(BK$1*365.25)) -> 5182.75 | CL17: =CK17/30.4375 -> 170.27515 | CM17: =CL17/12 -> 14.189596 | CN17: =INT(CM17) & " años y " & INT((CM17-INT(CM17))*12) & " meses" -> 14 años y 2 meses | CO17: =FV(CJ17,((AZ17-TODAY())/365.25)+BK$1,0,-R17) -> 7708168.2
B18: 16 | C18: Si | D18: Monterrey | E18: Sur | F18: Quantium | G18: Colonia | I18: C | J18: 12 | K18: Oeste | M18: 83.4 | N18: 2960655 | O18: No | P18: =Q18/N18 -> 0 | R18: =IF(O18="No",N18,N18-Q18) -> 2960655 | S18: =R18/M18 -> 35499.46 | U18: No | V18: No | X18: 4.5 | Y18: No | Z18: 2 | AA18: Si | AB18: Si | AC18: Si | AD18: Si | AE18: 4 | AF18: No | AH18: No | AI18: No | AJ18: 2 | AK18: Si | AM18: No | AP18: 0.1 | AQ18: =N18*AP18 -> 296065.5 | AR18: 0.1 | AS18: =AR18*N18 -> 296065.5 | AT18: 24 | AU18: =AS18/AT18 -> 12336.062 | AV18: =AQ18+AS18 -> 592131 | AW18: =1-AP18-AR18 -> 0.8 | AX18: =N18-AQ18-(AT18*AU18) -> 2368524 | AZ18: 45627 | BB18: =N18*0.03 -> 88819.65 | BC18: =N18*0.02 -> 59213.1 | BD18: 349000 | BE18: 190500 | BF18: =BB18+BC18+BD18+BE18 -> 687532.75 | BH18: =AX18 -> 2368524 | BI18: =AZ18+31 -> 45658 | BJ18: =BJ$1 -> 0.12 | BK18: =BK$1 -> 15 | BL18: =PMT(BJ18/12,BK18*12,-AX18) -> 28426.269 | BM18: =TIPOLOGÍAS!AZ18+(TIPOLOGÍAS!BK18*365.25) -> 51105.75 | BN18: =BL18*BK18*12 -> 5116728.3 | BP18: 32.5 | BQ18: =M18*BP18 -> 2710.5 | BR18: =AZ18+31 -> 45658 | BS18: =FV(BY18,BK$1-1,0,-BQ18) -> 6808.4296 | BT18: =TIPOLOGÍAS!AZ18+(TIPOLOGÍAS!BK18*365.25) -> 51105.75 | BU18: =FV(BY18,BK$1,-BQ18*12,0) -> 804865.2 | BW18: 9200 | BX18: =TIPOLOGÍAS!AZ18+62 -> 45689 | BY18: =BY$1 -> 0.068 | BZ18: =FV(BY18,BK$1,0,-BW18) -> 24680.651 | CA18: =TIPOLOGÍAS!AZ18+(TIPOLOGÍAS!BK18*365.25) -> 51105.75 | CB18: =CB$1 -> 11 | CC18: =FV(BY18,BK18,-BW18*CB18,0)-(2*BW18) -> 2485823 | CE18: =AV18+BF18+BN18+BU18 -> 7201257.3 | CF18: =CE18-CC18 -> 4715434.3 | CG18: =CF18/CL18 -> 28355.022 | CH18: =(RATE(CL18,-CG18,0,CO18))*12 -> 0.060712246 | CJ18: =CJ$1 -> 0.068 | CK18: =(AZ18-TODAY()+(BK$1*365.25)) -> 5061.75 | CL18: =CK18/30.4375 -> 166.29979 | CM18: =CL18/12 -> 13.858316 | CN18: =INT(CM18) & " años y " & INT((CM18-INT(CM18))*12) & " meses" -> 13 años y 10 meses | CO18: =FV(CJ18,((AZ18-TODAY())/365.25)+BK$1,0,-R18) -> 7367790.3
B19: 17 | C19: Si | D19: Monterrey | E19: Galerías | F19: AISEN | G19: Lívita 20 | I19: B | J19: 21 | K19: Sur | M19: 82.82 | N19: 2890654 | O19: No | P19: =Q19/N19 -> 0 | R19: =IF(O19="No",N19,N19-Q19) -> 2890654 | S19: =R19/M19 -> 34902.85 | U19: No | V19: No | X19: 4.7 | Y19: No | Z19: 1.5 | AA19: Si | AB19: Si | AC19: Si | AD19: No | AF19: No | AH19: No | AI19: No | AJ19: 1 | AK19: No | AM19: No | AP19: 0.05 | AQ19: =N19*AP19 -> 144532.7 | AR19: 0.05 | AS19: =AR19*N19 -> 144532.7 | AT19: 23 | AU19: =AS19/AT19 -> 6284.0304 | AV19: =AQ19+AS19 -> 289065.4 | AW19: =1-AP19-AR19 -> 0.9 | AX19: =N19-AQ19-(AT19*AU19) -> 2601588.6 | AZ19: 45597 | BB19: =N19*0.03 -> 86719.62 | BC19: =N19*0.02 -> 57813.08 | BD19: 235000 | BE19: 199500 | BF19: =BB19+BC19+BD19+BE19 -> 579032.7 | BH19: =AX19 -> 2601588.6 | BI19: =AZ19+31 -> 45628 | BJ19: =BJ$1 -> 0.12 | BK19: =BK$1 -> 15 | BL19: =PMT(BJ19/12,BK19*12,-AX19) -> 31223.435 | BM19: =TIPOLOGÍAS!AZ19+(TIPOLOGÍAS!BK19*365.25) -> 51075.75 | BN19: =BL19*BK19*12 -> 5620218.4 | BP19: 31.5 | BQ19: =M19*BP19 -> 2608.83 | BR19: =AZ19+31 -> 45628 | BS19: =FV(BY19,BK$1-1,0,-BQ19) -> 6553.0475 | BT19: =TIPOLOGÍAS!AZ19+(TIPOLOGÍAS!BK19*365.25) -> 51075.75 | BU19: =FV(BY19,BK$1,-BQ19*12,0) -> 774674.96 | BW19: 8540 | BX19: =TIPOLOGÍAS!AZ19+62 -> 45659 | BY19: =BY$1 -> 0.068 | BZ19: =FV(BY19,BK$1,0,-BW19) -> 22910.083 | CA19: =TIPOLOGÍAS!AZ19+(TIPOLOGÍAS!BK19*365.25) -> 51075.75 | CB19: =CB$1 -> 11 | CC19: =FV(BY19,BK19,-BW19*CB19,0)-(2*BW19) -> 2307492.2 | CE19: =AV19+BF19+BN19+BU19 -> 7262991.4 | CF19: =CE19-CC19 -> 4955499.2 | CG19: =CF19/CL19 -> 29976.252 | CH19: =(RATE(CL19,-CG19,0,CO19))*12 -> 0.050798219 | CJ19: =CJ$1 -> 0.068 | CK19: =(AZ19-TODAY()+(BK$1*365.25)) -> 5031.75 | CL19: =CK19/30.4375 -> 165.31417 | CM19: =CL19/12 -> 13.776181 | CN19: =INT(CM19) & " años y " & INT((CM19-INT(CM19))*12) & " meses" -> 13 años y 9 meses | CO19: =FV(CJ19,((AZ19-TODAY())/365.25)+BK$1,0,-R19) -> 7154822.3
B20: 18 | C20: Si | D20: Monterrey | E20: Maria Luisa | F20: Altio | G20: Novus | I20: A | J20: 20 | K20: Sur | M20: 54 | N20: 2820653 | O20: No | P20: =Q20/N20 -> 0 | R20: =IF(O20="No",N20,N20-Q20) -> 2820653 | S20: =R20/M20 -> 52234.315 | U20: No | V20: No | X20: 4.9 | Y20: No | Z20: 2 | AA20: Si | AB20: Si | AC20: Si | AD20: No | AF20: No | AH20: No | AI20: No | AJ20: 2 | AM20: No | AP20: 0.1 | AQ20: =N20*AP20 -> 282065.3 | AR20: 0.1 | AS20: =AR20*N20 -> 282065.3 | AT20: 26 | AU20: =AS20/AT20 -> 10848.665 | AV20: =AQ20+AS20 -> 564130.6 | AW20: =1-AP20-AR20 -> 0.8 | AX20: =N20-AQ20-(AT20*AU20) -> 2256522.4 | AZ20: 45261 | BB20: =N20*0.03 -> 84619.59 | BC20: =N20*0.02 -> 56413.06 | BD20: 255000 | BE20: 208500 | BF20: =BB20+BC20+BD20+BE20 -> 604532.65 | BH20: =AX20 -> 2256522.4 | BI20: =AZ20+31 -> 45292 | BJ20: =BJ$1 -> 0.12 | BK20: =BK$1 -> 15 | BL20: =PMT(BJ20/12,BK20*12,-AX20) -> 27082.061 | BM20: =TIPOLOGÍAS!AZ20+(TIPOLOGÍAS!BK20*365.25) -> 50739.75 | BN20: =BL20*BK20*12 -> 4874771 | BP20: 30.5 | BQ20: =M20*BP20 -> 1647 | BR20: =AZ20+31 -> 45292 | BS20: =FV(BY20,BK$1-1,0,-BQ20) -> 4137.0535 | BT20: =TIPOLOGÍAS!AZ20+(TIPOLOGÍAS!BK20*365.25) -> 50739.75 | BU20: =FV(BY20,BK$1,-BQ20*12,0) -> 489065.85 | BW20: 7880 | BX20: =TIPOLOGÍAS!AZ20+62 -> 45323 | BY20: =BY$1 -> 0.068 | BZ20: =FV(BY20,BK$1,0,-BW20) -> 21139.514 | CA20: =TIPOLOGÍAS!AZ20+(TIPOLOGÍAS!BK20*365.25) -> 50739.75 | CB20: =CB$1 -> 11 | CC20: =FV(BY20,BK20,-BW20*CB20,0)-(2*BW20) -> 2129161.5 | CE20: =AV20+BF20+BN20+BU20 -> 6532500.1 | CF20: =CE20-CC20 -> 4403338.7 | CG20: =CF20/CL20 -> 28542.112 | CH20: =(RATE(CL20,-CG20,0,CO20))*12 -> 0.059107599 | CJ20: =CJ$1 -> 0.068 | CK20: =(AZ20-TODAY()+(BK$1*365.25)) -> 4695.75 | CL20: =CK20/30.4375 -> 154.27515 | CM20: =CL20/12 -> 12.856263 | CN20: =INT(CM20) & " años y " & INT((CM20-INT(CM20))*12) & " meses" -> 12 años y 10 meses | CO20: =FV(CJ20,((AZ20-TODAY())/365.25)+BK$1,0,-R20) -> 6571570.9
B21: 19 | C21: Si | D21: Monterrey | E21: Cumbres | F21: Cuadro | G21: Avalon | I21: X | J21: 8 | K21: Este | M21: 81.66 | N21: 2750652 | O21: No | P21: =Q21/N21 -> 0 | R21: =IF(O21="No",N21,N21-Q21) -> 2750652 | S21: =R21/M21 -> 33684.203 | U21: No | V21: No | X21: 5.1 | Y21: No | Z21: 2 | AA21: Si | AB21: Si | AC21: Si | AD21: Si | AE21: 6.7 | AF21: No | AH21: No | AI21: No | AJ21: 2 | AM21: No | AP21: 0.1 | AQ21: =N21*AP21 -> 275065.2 | AR21: 0.1 | AS21: =AR21*N21 -> 275065.2 | AT21: 21 | AU21: =AS21/AT21 -> 13098.343 | AV21: =AQ21+AS21 -> 550130.4 | AW21: =1-AP21-AR21 -> 0.8 | AX21: =N21-AQ21-(AT21*AU21) -> 2200521.6 | AZ21: 45748 | BB21: =N21*0.03 -> 82519.56 | BC21: =N21*0.02 -> 55013.04 | BD21: 278500 | BE21: 217500 | BF21: =BB21+BC21+BD21+BE21 -> 633532.6 | BH21: =AX21 -> 2200521.6 | BI21: =AZ21+31 -> 45779 | BJ21: =BJ$1 -> 0.12 | BK21: =BK$1 -> 15 | BL21: =PMT(BJ21/12,BK21*12,-AX21) -> 26409.957 | BM21: =TIPOLOGÍAS!AZ21+(TIPOLOGÍAS!BK21*365.25) -> 51226.75 | BN21: =BL21*BK21*12 -> 4753792.3 | BP21: 29.5 | BQ21: =M21*BP21 -> 2408.97 | BR21: =AZ21+31 -> 45779 | BS21: =FV(BY21,BK$1-1,0,-BQ21) -> 6051.0247 | BT21: =TIPOLOGÍAS!AZ21+(TIPOLOGÍAS!BK21*365.25) -> 51226.75 | BU21: =FV(BY21,BK$1,-BQ21*12,0) -> 715327.84 | BW21: 7220 | BX21: =TIPOLOGÍAS!AZ21+62 -> 45810 | BY21: =BY$1 -> 0.068 | BZ21: =FV(BY21,BK$1,0,-BW21) -> 19368.946 | CA21: =TIPOLOGÍAS!AZ21+(TIPOLOGÍAS!BK21*365.25) -> 51226.75 | CB21: =CB$1 -> 11 | CC21: =FV(BY21,BK21,-BW21*CB21,0)-(2*BW21) -> 1950830.7 | CE21: =AV21+BF21+BN21+BU21 -> 6652783.2 | CF21: =CE21-CC21 -> 4701952.5 | CG21: =CF21/CL21 -> 27613.85 | CH21: =(RATE(CL21,-CG21,0,CO21))*12 -> 0.053128711 | CJ21: =CJ$1 -> 0.068 | CK21: =(AZ21-TODAY()+(BK$1*365.25)) -> 5182.75 | CL21: =CK21/30.4375 -> 170.27515 | CM21: =CL21/12 -> 14.189596 | CN21: =INT(CM21) & " años y " & INT((CM21-INT(CM21))*12) & " meses" -> 14 años y 2 meses | CO21: =FV(CJ21,((AZ21-TODAY())/365.25)+BK$1,0,-R21) -> 6996006.2
B22: 20 | C22: Si | D22: Monterrey | E22: Contry | F22: Creare | G22: Arena Fundidora | I22: C | J22: 14 | K22: Oeste | M22: 81.08 | N22: 2680651 | O22: No | P22: =Q22/N22 -> 0 | R22: =IF(O22="No",N22,N22-Q22) -> 2680651 | S22: =R22/M22 -> 33061.803 | U22: No | V22: No | X22: 5.3 | Y22: No | Z22: 2 | AA22: Si | AB22: Si | AC22: Si | AD22: Si | AE22: 5.5 | AF22: No | AH22: No | AI22: No | AJ22: 2 | AM22: No | AP22: 0.1 | AQ22: =N22*AP22 -> 268065.1 | AR22: 0.1 | AS22: =AR22*N22 -> 268065.1 | AT22: 18 | AU22: =AS22/AT22 -> 14892.506 | AV22: =AQ22+AS22 -> 536130.2 | AW22: =1-AP22-AR22 -> 0.8 | AX22: =N22-AQ22-(AT22*AU22) -> 2144520.8 | AZ22: 45627 | BB22: =N22*0.03 -> 80419.53 | BC22: =N22*0.02 -> 53613.02 | BD22: 302000 | BE22: 172500 | BF22: =BB22+BC22+BD22+BE22 -> 608532.55 | BH22: =AX22 -> 2144520.8 | BI22: =AZ22+31 -> 45658 | BJ22: =BJ$1 -> 0.12 | BK22: =BK$1 -> 15 | BL22: =PMT(BJ22/12,BK22*12,-AX22) -> 25737.854 | BM22: =TIPOLOGÍAS!AZ22+(TIPOLOGÍAS!BK22*365.25) -> 51105.75 | BN22: =BL22*BK22*12 -> 4632813.7 | BP22: 28.5 | BQ22: =M22*BP22 -> 2310.78 | BR22: =AZ22+31 -> 45658 | BS22: =FV(BY22,BK$1-1,0,-BQ22) -> 5804.384 | BT22: =TIPOLOGÍAS!AZ22+(TIPOLOGÍAS!BK22*365.25) -> 51105.75 | BU22: =FV(BY22,BK$1,-BQ22*12,0) -> 686170.96 | BW22: 6560 | BX22: =TIPOLOGÍAS!AZ22+62 -> 45689 | BY22: =BY$1 -> 0.068 | BZ22: =FV(BY22,BK$1,0,-BW22) -> 17598.378 | CA22: =TIPOLOGÍAS!AZ22+(TIPOLOGÍAS!BK22*365.25) -> 51105.75 | CB22: =CB$1 -> 11 | CC22: =FV(BY22,BK22,-BW22*CB22,0)-(2*BW22) -> 1772499.9 | CE22: =AV22+BF22+BN22+BU22 -> 6463647.4 | CF22: =CE22-CC22 -> 4691147.5 | CG22: =CF22/CL22 -> 28208.979 | CH22: =(RATE(CL22,-CG22,0,CO22))*12 -> 0.048505606 | CJ22: =CJ$1 -> 0.068 | CK22: =(AZ22-TODAY()+(BK$1*365.25)) -> 5061.75 | CL22: =CK22/30.4375 -> 166.29979 | CM22: =CL22/12 -> 13.858316 | CN22: =INT(CM22) & " años y " & INT((CM22-INT(CM22))*12) & " meses" -> 13 años y 10 meses | CO22: =FV(CJ22,((AZ22-TODAY())/365.25)+BK$1,0,-R22) -> 6670981.4
B23: 21 | C23: Si | D23: Monterrey | E23: Valle Oriente | F23: Quantium | G23: Arena Calzada | I23: B | J23: 7 | K23: Sur | M23: 111 | N23: 2610650 | O23: No | P23: =Q23/N23 -> 0 | R23: =IF(O23="No",N23,N23-Q23) -> 2610650 | S23: =R23/M23 -> 23519.369 | U23: No | V23: No | X23: 5.5 | Y23: No | Z23: 1 | AA23: Si | AB23: Si | AC23: Si | AD23: No | AF23: No | AH23: No | AI23: No | AJ23: 2 | AM23: No | AP23: 0.1 | AQ23: =N23*AP23 -> 261065 | AR23: 0.1 | AS23: =AR23*N23 -> 261065 | AT23: 30 | AU23: =AS23/AT23 -> 8702.1667 | AV23: =AQ23+AS23 -> 522130 | AW23: =1-AP23-AR23 -> 0.8 | AX23: =N23-AQ23-(AT23*AU23) -> 2088520 | AZ23: 45597 | BB23: =N23*0.03 -> 78319.5 | BC23: =N23*0.02 -> 52213 | BD23: 235000 | BE23: 181500 | BF23: =BB23+BC23+BD23+BE23 -> 547032.5 | BH23: =AX23 -> 2088520 | BI23: =AZ23+31 -> 45628 | BJ23: =BJ$1 -> 0.12 | BK23: =BK$1 -> 15 | BL23: =PMT(BJ23/12,BK23*12,-AX23) -> 25065.75 | BM23: =TIPOLOGÍAS!AZ23+(TIPOLOGÍAS!BK23*365.25) -> 51075.75 | BN23: =BL23*BK23*12 -> 4511835 | BP23: 27.5 | BQ23: =M23*BP23 -> 3052.5 | BR23: =AZ23+31 -> 45628 | BS23: =FV(BY23,BK$1-1,0,-BQ23) -> 7667.4899 | BT23: =TIPOLOGÍAS!AZ23+(TIPOLOGÍAS!BK23*365.25) -> 51075.75 | BU23: =FV(BY23,BK$1,-BQ23*12,0) -> 906419.85 | BW23: 5900 | BX23: =TIPOLOGÍAS!AZ23+62 -> 45659 | BY23: =BY$1 -> 0.068 | BZ23: =FV(BY23,BK$1,0,-BW23) -> 15827.809 | CA23: =TIPOLOGÍAS!AZ23+(TIPOLOGÍAS!BK23*365.25) -> 51075.75 | CB23: =CB$1 -> 11 | CC23: =FV(BY23,BK23,-BW23*CB23,0)-(2*BW23) -> 1594169.1 | CE23: =AV23+BF23+BN23+BU23 -> 6487417.4 | CF23: =CE23-CC23 -> 4893248.2 | CG23: =CF23/CL23 -> 29599.691 | CH23: =(RATE(CL23,-CG23,0,CO23))*12 -> 0.038934043 | CJ23: =CJ$1 -> 0.068 | CK23: =(AZ23-TODAY()+(BK$1*365.25)) -> 5031.75 | CL23: =CK23/30.4375 -> 165.31417 | CM23: =CL23/12 -> 13.776181 | CN23: =INT(CM23) & " años y " & INT((CM23-INT(CM23))*12) & " meses" -> 13 años y 9 meses | CO23: =FV(CJ23,((AZ23-TODAY())/365.25)+BK$1,0,-R23) -> 6461768.4
B24: 22 | C24: Si | D24: Monterrey | E24: Sur | F24: AISEN | G24: Moca Azul | I24: A | J24: 12 | K24: Sur | M24: 79.92 | N24: 2540649 | O24: No | P24: =Q24/N24 -> 0 | R24: =IF(O24="No",N24,N24-Q24) -> 2540649 | S24: =R24/M24 -> 31789.902 | U24: No | V24: No | X24: 5.7 | Y24: No | Z24: 2 | AA24: Si | AB24: Si | AC24: Si | AD24: No | AF24: No | AH24: No | AI24: No | AJ24: 1 | AK24: No | AM24: No | AP24: 0.05 | AQ24: =N24*AP24 -> 127032.45 | AR24: 0.05 | AS24: =AR24*N24 -> 127032.45 | AT24: 24 | AU24: =AS24/AT24 -> 5293.0188 | AV24: =AQ24+AS24 -> 254064.9 | AW24: =1-AP24-AR24 -> 0.9 | AX24: =N24-AQ24-(AT24*AU24) -> 2286584.1 | AZ24: 45261 | BB24: =N24*0.03 -> 76219.47 | BC24: =N24*0.02 -> 50812.98 | BD24: 255000 | BE24: 190500 | BF24: =BB24+BC24+BD24+BE24 -> 572532.45 | BH24: =AX24 -> 2286584.1 | BI24: =AZ24+31 -> 45292 | BJ24: =BJ$1 -> 0.12 | BK24: =BK$1 -> 15 | BL24: =PMT(BJ24/12,BK24*12,-AX24) -> 27442.852 | BM24: =TIPOLOGÍAS!AZ24+(TIPOLOGÍAS!BK24*365.25) -> 50739.75 | BN24: =BL24*BK24*12 -> 4939713.4 | BP24: 26.5 | BQ24: =M24*BP24 -> 2117.88 | BR24: =AZ24+31 -> 45292 | BS24: =FV(BY24,BK$1-1,0,-BQ24) -> 5319.8439 | BT24: =TIPOLOGÍAS!AZ24+(TIPOLOGÍAS!BK24*365.25) -> 50739.75 | BU24: =FV(BY24,BK$1,-BQ24*12,0) -> 628890.57 | BW24: 5240 | BX24: =TIPOLOGÍAS!AZ24+62 -> 45323 | BY24: =BY$1 -> 0.068 | BZ24: =FV(BY24,BK$1,0,-BW24) -> 14057.241 | CA24: =TIPOLOGÍAS!AZ24+(TIPOLOGÍAS!BK24*365.25) -> 50739.75 | CB24: =CB$1 -> 11 | CC24: =FV(BY24,BK24,-BW24*CB24,0)-(2*BW24) -> 1415838.3 | CE24: =AV24+BF24+BN24+BU24 -> 6395201.3 | CF24: =CE24-CC24 -> 4979363 | CG24: =CF24/CL24 -> 32275.858 | CH24: =(RATE(CL24,-CG24,0,CO24))*12 -> 0.026355462 | CJ24: =CJ$1 -> 0.068 | CK24: =(AZ24-TODAY()+(BK$1*365.25)) -> 4695.75 | CL24: =CK24/30.4375 -> 154.27515 | CM24: =CL24/12 -> 12.856263 | CN24: =INT(CM24) & " años y " & INT((CM24-INT(CM24))*12) & " meses" -> 12 años y 10 meses | CO24: =FV(CJ24,((AZ24-TODAY())/365.25)+BK$1,0,-R24) -> 5919216.2
B25: 23 | C25: Si | D25: Monterrey | E25: Galerías | F25: Altio | G25: Moca Verde | I25: X | J25: 21 | K25: Este | M25: 79.34 | N25: 2470648 | O25: No | P25: =Q25/N25 -> 0 | R25: =IF(O25="No",N25,N25-Q25) -> 2470648 | S25: =R25/M25 -> 31140.005 | U25: No | V25: No | X25: 5.9 | Y25: No | Z25: 1 | AA25: Si | AB25: Si | AC25: Si | AD25: Si | AE25: 6 | AF25: No | AH25: No | AI25: No | AJ25: 2 | AM25: No | AP25: 0.1 | AQ25: =N25*AP25 -> 247064.8 | AR25: 0.1 | AS25: =AR25*N25 -> 247064.8 | AT25: 23 | AU25: =AS25/AT25 -> 10741.948 | AV25: =AQ25+AS25 -> 494129.6 | AW25: =1-AP25-AR25 -> 0.8 | AX25: =N25-AQ25-(AT25*AU25) -> 1976518.4 | AZ25: 45748 | BB25: =N25*0.03 -> 74119.44 | BC25: =N25*0.02 -> 49412.96 | BD25: 278500 | BE25: 199500 | BF25: =BB25+BC25+BD25+BE25 -> 601532.4 | BH25: =AX25 -> 1976518.4 | BI25: =AZ25+31 -> 45779 | BJ25: =BJ$1 -> 0.12 | BK25: =BK$1 -> 15 | BL25: =PMT(BJ25/12,BK25*12,-AX25) -> 23721.543 | BM25: =TIPOLOGÍAS!AZ25+(TIPOLOGÍAS!BK25*365.25) -> 51226.75 | BN25: =BL25*BK25*12 -> 4269877.7 | BP25: 25.5 | BQ25: =M25*BP25 -> 2023.17 | BR25: =AZ25+31 -> 45779 | BS25: =FV(BY25,BK$1-1,0,-BQ25) -> 5081.9445 | BT25: =TIPOLOGÍAS!AZ25+(TIPOLOGÍAS!BK25*365.25) -> 51226.75 | BU25: =FV(BY25,BK$1,-BQ25*12,0) -> 600767.06 | BW25: 4580 | BX25: =TIPOLOGÍAS!AZ25+62 -> 45810 | BY25: =BY$1 -> 0.068 | BZ25: =FV(BY25,BK$1,0,-BW25) -> 12286.672 | CA25: =TIPOLOGÍAS!AZ25+(TIPOLOGÍAS!BK25*365.25) -> 51226.75 | CB25: =CB$1 -> 11 | CC25: =FV(BY25,BK25,-BW25*CB25,0)-(2*BW25) -> 1237507.5 | CE25: =AV25+BF25+BN25+BU25 -> 5966306.7 | CF25: =CE25-CC25 -> 4728799.2 | CG25: =CF25/CL25 -> 27771.516 | CH25: =(RATE(CL25,-CG25,0,CO25))*12 -> 0.038608904 | CJ25: =CJ$1 -> 0.068 | CK25: =(AZ25-TODAY()+(BK$1*365.25)) -> 5182.75 | CL25: =CK25/30.4375 -> 170.27515 | CM25: =CL25/12 -> 14.189596 | CN25: =INT(CM25) & " años y " & INT((CM25-INT(CM25))*12) & " meses" -> 14 años y 2 meses | CO25: =FV(CJ25,((AZ25-TODAY())/365.25)+BK$1,0,-R25) -> 6283844.3
B26: 24 | C26: Si | D26: Monterrey | E26: Maria Luisa | F26: Cuadro | G26: Colonia | I26: C | J26: 20 | K26: Oeste | M26: 99 | N26: 2400647 | O26: No | P26: =Q26/N26 -> 0 | R26: =IF(O26="No",N26,N26-Q26) -> 2400647 | S26: =R26/M26 -> 24248.96 | U26: No | V26: No | X26: 6.1 | Y26: No | Z26: 1 | AA26: Si | AB26: Si | AC26: Si | AD26: Si | AE26: 6 | AF26: No | AH26: No | AI26: No | AJ26: 2 | AK26: No | AM26: No | AP26: 0.1 | AQ26: =N26*AP26 -> 240064.7 | AR26: 0.1 | AS26: =AR26*N26 -> 240064.7 | AT26: 26 | AU26: =AS26/AT26 -> 9233.2577 | AV26: =AQ26+AS26 -> 480129.4 | AW26: =1-AP26-AR26 -> 0.8 | AX26: =N26-AQ26-(AT26*AU26) -> 1920517.6 | AZ26: 45627 | BB26: =N26*0.03 -> 72019.41 | BC26: =N26*0.02 -> 48012.94 | BD26: 302000 | BE26: 208500 | BF26: =BB26+BC26+BD26+BE26 -> 630532.35 | BH26: =AX26 -> 1920517.6 | BI26: =AZ26+31 -> 45658 | BJ26: =BJ$1 -> 0.12 | BK26: =BK$1 -> 15 | BL26: =PMT(BJ26/12,BK26*12,-AX26) -> 23049.439 | BM26: =TIPOLOGÍAS!AZ26+(TIPOLOGÍAS!BK26*365.25) -> 51105.75 | BN26: =BL26*BK26*12 -> 4148899 | BP26: 24.5 | BQ26: =M26*BP26 -> 2425.5 | BR26: =AZ26+31 -> 45658 | BS26: =FV(BY26,BK$1-1,0,-BQ26) -> 6092.546 | BT26: =TIPOLOGÍAS!AZ26+(TIPOLOGÍAS!BK26*365.25) -> 51105.75 | BU26: =FV(BY26,BK$1,-BQ26*12,0) -> 720236.32 | BW26: 3920 | BX26: =TIPOLOGÍAS!AZ26+62 -> 45689 | BY26: =BY$1 -> 0.068 | BZ26: =FV(BY26,BK$1,0,-BW26) -> 10516.104 | CA26: =TIPOLOGÍAS!AZ26+(TIPOLOGÍAS!BK26*365.25) -> 51105.75 | CB26: =CB$1 -> 11 | CC26: =FV(BY26,BK26,-BW26*CB26,0)-(2*BW26) -> 1059176.8 | CE26: =AV26+BF26+BN26+BU26 -> 5979797.1 | CF26: =CE26-CC26 -> 4920620.3 | CG26: =CF26/CL26 -> 29588.854 | CH26: =(RATE(CL26,-CG26,0,CO26))*12 -> 0.027334612 | CJ26: =CJ$1 -> 0.068 | CK26: =(AZ26-TODAY()+(BK$1*365.25)) -> 5061.75 | CL26: =CK26/30.4375 -> 166.29979 | CM26: =CL26/12 -> 13.858316 | CN26: =INT(CM26) & " años y " & INT((CM26-INT(CM26))*12) & " meses" -> 13 años y 10 meses | CO26: =FV(CJ26,((AZ26-TODAY())/365.25)+BK$1,0,-R26) -> 5974172.5
B27: 25 | C27: Si | D27: Monterrey | E27: Galerías | F27: Creare | G27: Moca Azul | I27: B | J27: 20 | K27: Sur | M27: 78.18 | N27: 2330646 | O27: No | P27: =Q27/N27 -> 0 | R27: =IF(O27="No",N27,N27-Q27) -> 2330646 | S27: =R27/M27 -> 29811.282 | U27: No | V27: No | X27: 6.3 | Y27: No | Z27: 2 | AA27: Si | AB27: Si | AC27: Si | AD27: No | AF27: No | AH27: No | AI27: No | AJ27: 2 | AK27: No | AM27: No | AP27: 0.1 | AQ27: =N27*AP27 -> 233064.6 | AR27: 0.1 | AS27: =AR27*N27 -> 233064.6 | AT27: 29 | AU27: =AS27/AT27 -> 8036.7103 | AV27: =AQ27+AS27 -> 466129.2 | AW27: =1-AP27-AR27 -> 0.8 | AX27: =N27-AQ27-(AT27*AU27) -> 1864516.8 | AZ27: 45597 | BB27: =N27*0.03 -> 69919.38 | BC27: =N27*0.02 -> 46612.92 | BD27: 325500 | BE27: 217500 | BF27: =BB27+BC27+BD27+BE27 -> 659532.3 | BH27: =AX27 -> 1864516.8 | BI27: =AZ27+31 -> 45628 | BJ27: =BJ$1 -> 0.12 | BK27: =BK$1 -> 15 | BL27: =PMT(BJ27/12,BK27*12,-AX27) -> 22377.335 | BM27: =TIPOLOGÍAS!AZ27+(TIPOLOGÍAS!BK27*365.25) -> 51075.75 | BN27: =BL27*BK27*12 -> 4027920.3 | BP27: 23.5 | BQ27: =M27*BP27 -> 1837.23 | BR27: =AZ27+31 -> 45628 | BS27: =FV(BY27,BK$1-1,0,-BQ27) -> 4614.8869 | BT27: =TIPOLOGÍAS!AZ27+(TIPOLOGÍAS!BK27*365.25) -> 51075.75 | BU27: =FV(BY27,BK$1,-BQ27*12,0) -> 545553.4 | BW27: 3260 | BX27: =TIPOLOGÍAS!AZ27+62 -> 45659 | BY27: =BY$1 -> 0.068 | BZ27: =FV(BY27,BK$1,0,-BW27) -> 8745.5352 | CA27: =TIPOLOGÍAS!AZ27+(TIPOLOGÍAS!BK27*365.25) -> 51075.75 | CB27: =CB$1 -> 11 | CC27: =FV(BY27,BK27,-BW27*CB27,0)-(2*BW27) -> 880845.98 | CE27: =AV27+BF27+BN27+BU27 -> 5699135.2 | CF27: =CE27-CC27 -> 4818289.2 | CG27: =CF27/CL27 -> 29146.257 | CH27: =(RATE(CL27,-CG27,0,CO27))*12 -> 0.025569977 | CJ27: =CJ$1 -> 0.068 | CK27: =(AZ27-TODAY()+(BK$1*365.25)) -> 5031.75 | CL27: =CK27/30.4375 -> 165.31417 | CM27: =CL27/12 -> 13.776181 | CN27: =INT(CM27) & " años y " & INT((CM27-INT(CM27))*12) & " meses" -> 13 años y 9 meses | CO27: =FV(CJ27,((AZ27-TODAY())/365.25)+BK$1,0,-R27) -> 5768714.6
B28: 26 | C28: Si | D28: Monterrey | E28: Maria Luisa | F28: Cuadro | G28: Moca Verde | I28: A | J28: 8 | K28: Sur | M28: 77.6 | N28: 2260645 | O28: No | P28: =Q28/N28 -> 0 | R28: =IF(O28="No",N28,N28-Q28) -> 2260645 | S28: =R28/M28 -> 29132.023 | U28: No | V28: No | X28: 6.5 | Y28: No | Z28: 1 | AA28: Si | AB28: Si | AC28: Si | AD28: No | AF28: No | AH28: No | AI28: No | AJ28: 2 | AM28: No | AP28: 0.15 | AQ28: =N28*AP28 -> 339096.75 | AR28: 0.15 | AS28: =AR28*N28 -> 339096.75 | AT28: 32 | AU28: =AS28/AT28 -> 10596.773 | AV28: =AQ28+AS28 -> 678193.5 | AW28: =1-AP28-AR28 -> 0.7 | AX28: =N28-AQ28-(AT28*AU28) -> 1582451.5 | AZ28: 45261 | BB28: =N28*0.03 -> 67819.35 | BC28: =N28*0.02 -> 45212.9 | BD28: 349000 | BE28: 226500 | BF28: =BB28+BC28+BD28+BE28 -> 688532.25 | BH28: =AX28 -> 1582451.5 | BI28: =AZ28+31 -> 45292 | BJ28: =BJ$1 -> 0.12 | BK28: =BK$1 -> 15 | BL28: =PMT(BJ28/12,BK28*12,-AX28) -> 18992.078 | BM28: =TIPOLOGÍAS!AZ28+(TIPOLOGÍAS!BK28*365.25) -> 50739.75 | BN28: =BL28*BK28*12 -> 3418574 | BP28: 22.5 | BQ28: =M28*BP28 -> 1746 | BR28: =AZ28+31 -> 45292 | BS28: =FV(BY28,BK$1-1,0,-BQ28) -> 4385.7288 | BT28: =TIPOLOGÍAS!AZ28+(TIPOLOGÍAS!BK28*365.25) -> 50739.75 | BU28: =FV(BY28,BK$1,-BQ28*12,0) -> 518463.25 | BW28: 2600 | BX28: =TIPOLOGÍAS!AZ28+62 -> 45323 | BY28: =BY$1 -> 0.068 | BZ28: =FV(BY28,BK$1,0,-BW28) -> 6974.9667 | CA28: =TIPOLOGÍAS!AZ28+(TIPOLOGÍAS!BK28*365.25) -> 50739.75 | CB28: =CB$1 -> 11 | CC28: =FV(BY28,BK28,-BW28*CB28,0)-(2*BW28) -> 702515.2 | CE28: =AV28+BF28+BN28+BU28 -> 5303762.9 | CF28: =CE28-CC28 -> 4601247.7 | CG28: =CF28/CL28 -> 29824.943 | CH28: =(RATE(CL28,-CG28,0,CO28))*12 -> 0.020711595 | CJ28: =CJ$1 -> 0.068 | CK28: =(AZ28-TODAY()+(BK$1*365.25)) -> 4695.75 | CL28: =CK28/30.4375 -> 154.27515 | CM28: =CL28/12 -> 12.856263 | CN28: =INT(CM28) & " años y " & INT((CM28-INT(CM28))*12) & " meses" -> 12 años y 10 meses | CO28: =FV(CJ28,((AZ28-TODAY())/365.25)+BK$1,0,-R28) -> 5266861.6
B29: 27 | C29: Si | D29: Monterrey | E29: Galerías | F29: Creare | G29: Colonia | I29: X | J29: 14 | K29: Este | M29: 56 | N29: 2190644 | O29: No | P29: =Q29/N29 -> 0 | R29: =IF(O29="No",N29,N29-Q29) -> 2190644 | S29: =R29/M29 -> 39118.643 | U29: No | V29: No | X29: 6.7 | Y29: No | Z29: 1 | AA29: Si | AB29: Si | AC29: Si | AD29: Si | AE29: 5 | AF29: No | AH29: No | AI29: No | AJ29: 2 | AM29: No | AP29: 0.2 | AQ29: =N29*AP29 -> 438128.8 | AR29: 0.2 | AS29: =AR29*N29 -> 438128.8 | AT29: 35 | AU29: =AS29/AT29 -> 12517.966 | AV29: =AQ29+AS29 -> 876257.6 | AW29: =1-AP29-AR29 -> 0.6 | AX29: =N29-AQ29-(AT29*AU29) -> 1314386.4 | AZ29: 45748 | BB29: =N29*0.03 -> 65719.32 | BC29: =N29*0.02 -> 43812.88 | BD29: 349000 | BE29: 235500 | BF29: =BB29+BC29+BD29+BE29 -> 694032.2 | BH29: =AX29 -> 1314386.4 | BI29: =AZ29+31 -> 45779 | BJ29: =BJ$1 -> 0.12 | BK29: =BK$1 -> 15 | BL29: =PMT(BJ29/12,BK29*12,-AX29) -> 15774.846 | BM29: =TIPOLOGÍAS!AZ29+(TIPOLOGÍAS!BK29*365.25) -> 51226.75 | BN29: =BL29*BK29*12 -> 2839472.2 | BP29: 21.5 | BQ29: =M29*BP29 -> 1204 | BR29: =AZ29+31 -> 45779 | BS29: =FV(BY29,BK$1-1,0,-BQ29) -> 3024.2941 | BT29: =TIPOLOGÍAS!AZ29+(TIPOLOGÍAS!BK29*365.25) -> 51226.75 | BU29: =FV(BY29,BK$1,-BQ29*12,0) -> 357519.9 | BW29: 1940 | BX29: =TIPOLOGÍAS!AZ29+62 -> 45810 | BY29: =BY$1 -> 0.068 | BZ29: =FV(BY29,BK$1,0,-BW29) -> 5204.3982 | CA29: =TIPOLOGÍAS!AZ29+(TIPOLOGÍAS!BK29*365.25) -> 51226.75 | CB29: =CB$1 -> 11 | CC29: =FV(BY29,BK29,-BW29*CB29,0)-(2*BW29) -> 524184.42 | CE29: =AV29+BF29+BN29+BU29 -> 4767281.9 | CF29: =CE29-CC29 -> 4243097.5 | CG29: =CF29/CL29 -> 24919.064 | CH29: =(RATE(CL29,-CG29,0,CO29))*12 -> 0.037054387 | CJ29: =CJ$1 -> 0.068 | CK29: =(AZ29-TODAY()+(BK$1*365.25)) -> 5182.75 | CL29: =CK29/30.4375 -> 170.27515 | CM29: =CL29/12 -> 14.189596 | CN29: =INT(CM29) & " años y " & INT((CM29-INT(CM29))*12) & " meses" -> 14 años y 2 meses | CO29: =FV(CJ29,((AZ29-TODAY())/365.25)+BK$1,0,-R29) -> 5571682.3
A30: Admin
A31: Updater
A32: Profiler
A33: Finanzas
A34: Asesor
A35: Desarrollador
A38: Ultima fecha de actualizacion | AT38: Automatico
AL39: Cambios NO retroactivos
A40: Registro de Ventas, precio comision, fechas

Sheet LANDING
B1: HEADER
B2: Slogan
B5: BODY
B6: Mensaje de impacto
B11: FILTRO
B12: Objetivo | D12: Hacer Patrimonio y Cobrar Rentas
B13: Ciudad | D13: Hacer Patrimonio y Usarlo Yo
B14: Zona | D14: Esperar a la mayor Plusvalía y Vender
B15: Tamaño Minimo y Máximo
B16: Recámaras
B17: Baños
B18: Presupuesto Mínimo y Máximo
B19: Enganche
B20: Fecha estimada de Entrega
B23: CONTENIDO
B24: Mas visitados
B27: ESTADÍSTICAS
B31: ULTIMOS
B34: VENTAJAS
B36: Te acompañamos en todo el proceso hasta la escrituracion
... B50: Todos los inmuebles nuevos a tu medida
A51: 1 | B51: Hoy puedes tener una oportunidad genial para ti y separarla!
A52: 1 | B52: Revolucionamos los bienes raíces en México.
B53: Construye tu patrimonio ahora
B54: Encontrar tu hogar soñado nunca fue tan fácil
A55: 1 | B55: Tu asesor inmobiliario de confianza
B56: Elige tu próxima casa y deja todo el proceso en nuestras manos
B57: Sólo las mejores opciones en Monterrey
B58: NO TODAS
B60: DIFERENCIADORES
B61: Filtros
B62: Esquema financiero
B63: Compartivos
B64: Asesoría Personal
B69: CUANDO SE PRESENTE LA INFORMACIÓN FINANCIERA:
B70: Te vamos a dar un esquema financiero de retorno
B71: Te vamos a sesorar personalmente para que tomes la mejor decision
B72: No te va a salir mas caro por hacerlo con nosotros
B73: Analiza las opciones de inversión considerando lo que es importante para ti

Sheet PROSPECTOS
B1: 1 | C1: 2 | D1: 3 | E1: 4 | F1: 5 | G1: 6 | H1: 7 | I1: 8 | J1: 9 | K1: 10 | L1: 11 | M1: 12 | N1: 13 | O1: 14 | P1: 15 | Q1: 16 | R1: 17 | S1: 18 | T1: 19 | U1: 20 | V1: 21 | W1: 22
B2: FECHA | C2: HORA | D2: ASESOR | E2: CIUDAD | F2: ZONA | G2: DESARROLLADOR | H2: DESARROLLO | I2: TIPOLOGÍA | J2: NOMBRE | K2: APELLIDO | L2: TELEFONO | M2: CORREO | N2: TIPO | O2: PERFIL | P2: CÓMO LLEGA | Q2: BROKER EXTERNO | R2: ESTATUS | S2: EMBUDO | T2: COMO PAGA | U2: POSITIVOS | V2: NEGATIVOS | W2: COMENTARIOS
P4: LANDING | U4: Cat e Input | V4: Cat e Input
B5: * | C5: * | E5: * | F5: * | G5: * | H5: * | I5: * | J5: * | K5: * | L5: * | M5: * | N5: * | P5: *
B7: PERFILES | C7: PUEDE MODIFICAR | I7: TODO | J7: ASESOR | K7: STATUS | M7: FILTRAR
B8: ADMIN | D8: LANDING | H8: 1 | M8: FECHA
B9: PROFILER | H9: 2
B10: ASESOR | H10: 3 | M10: ASESOR
H11: 4
B12: Alerta si algun prospecto esta repetido | H12: 5
B13: Si llega por landing, sólo el ADMIN puede modificarlo | H13: 6
B14: * Se registra automático | H14: 7
H15: 8
H16: 9
H17: 10
H18: 11
H19: 12
H20: 13 | M20: TIPO
H21: 14
H22: 15 | M22: COMO LLEGA
H23: 16
H24: 17
H25: 18 | M25: EMBUDO
H26: 19
H27: 20 | M27: POSITIVOS
H28: 21 | M28: NEGATIVOS
H29: 22

Sheet DOCUMENTOS
A2: DESARROLLADORES | C2: Desarrollador 1 | E2: Legales | G2: Identidad
G3: Corporativo
G4: Convenios
E6: Desarrollo A | G6: Legales | H6: Identidad
H7: Convenios
H8: Permisos
H9: Fideicomiso
H10: Oferta y Contrato
G12: Venta | H12: Imágenes
H13: Videos
H14: Brochures y Flyers
H15: Promociones
H16: Acabados y Equipamiento
H17: Listas de Precios
H18: Ejercicios
G20: Tiología X | H20: Venta | I20: Imágenes
I21: Videos
G23: Tiología Y | H23: Venta | I23: Imágenes
I24: Videos
G26: Tiología Z | H26: Venta | I26: Imágenes
I27: Videos
A29: CLIENTES | C29: Cliente A | E29: Documentos de Identidad
E30: Cotizaciones
E31: Oferta y Contrato
E32: Ejercicios
A34: DE TRABAJO | C34: Recibo de Separación
C35: Cartas
C36: Checklists
C37: 7 Productos
A39: Dashboard
A40: Desarrolladores
A41: Desarrollos
A42: Tipologías
A43: Prospectos
A44: Documentos
A45: Catalogos
A51: (Listado de Carpetas de, Desarrolladores, Desarrollos, Tipologías, Prospectos.
A53: Falta añadir, sub carpetas, funcionalidad para compartir a clientes, para que puedan subir sus ines los clientes, o ver documentos que el admin compartira)
A56: Organizar las cotizaciones por desarrollo?
A57: Locales
A58: Oficinas

Sheet VISTAS Y USUARIOS
A3: DESARROLLADORES | D3: ID | F3: ACTIVO | G3: DESARROLLADOR | H3: RAZON SOCIAL | I3: RFC | J3: DOMICILIO | K3: ANTIGUEDAD | M3: TIPOS | N3: REPRESENTANTE | O3: CONTACTO | R3: LEGALES
E4: TIPO | O4: NOMBRE | P4: TELÉFONO | Q4: CORREO | AB4: asd
C5: ADMIN
C6: UPDATER
C7: PROFILER
C8: FINANZAS
C9: ASESOR
C10: DESARR.
A13: DESARROLLOS | D13: ID | E13: ACTIVO | F13: DESARROLLADOR | G13: DESARROLLO | H13: CIUDAD | I13: ZONA 1 | J13: ZONA 2 | K13: ZONA 3 | L13: TIPO | M13: NIVEL | N13: TORRES | O13: NIVELES | P13: AMENIDADES | Q13: EFICIENCIA | R13: OTROS | S13: TAMAÑO | U13: LOCK OFF | V13: REC | X13: ACABADOS | Y13: UNIDADES Y METROS CUADRADOS | AG13: INICIO PREVENTA | AH13: TIEMPO TRANSC. | AI13: DEPAS | AL13: LOCALES | AO13: OFICINAS | AR13: SALUD | AU13: INICIO OBRA | AW13: ENTREGA | AY13: VENTAS | BB13: PAGOS | BE13: COMERCILIZADORA | BF13: ARQUITECTURA | BG13: LOCATION | BH13: LEGALES | BI13: VENTA
S14: DESDE | T14: HASTA | V14: DESDE | W14: HASTA | Y14: DEPAS | AA14: LOCALES | AC14: OFICINAS | AE14: SALUD | AI14: UNIDADES | AJ14: VENDIDAS | AK14: % | AL14: UNIDADES | AM14: VENDIDAS | AN14: % | AO14: UNIDADES | AP14: VENDIDAS | AQ14: % | AR14: UNIDADES | AS14: VENDIDAS | AT14: % | AU14: PROYECTADO | AV14: REAL | AW14: PROYECTADA | AX14: ACTUALIZADA | AY14: NOMBRE | AZ14: TELÉFONO | BA14: CORREO | BB14: NOMBRE | BC14: TELÉFONO | BD14: CORREO
C15: Admin
C16: Updater
C17: Profiler
C18: Finanzas
C19: Asesor
C20: Desarrollador
AI21: N/A | AL21: N/A | AO21: N/A | AR21: N/A | BE21: N/A | BF21: N/A
A23: TIPOLOGÍAS | D23: ID | E23: ACTIVO | J23: GENERALES | M23: PRECIO | X23: DISTRIBUCIÓN | AM23: CAJONES | AP23: BODEGA | AU23: ESQUEMA DE PAGO | BD23: ENTREGA | BE23: 0.03 | BF23: 0.025 | BL23: 0.105 | BM23: 15 | BN23: CRÉDITO HIPOTECARIO | BQ23: MANTENIMIENTO | BW23: RENTA | BY23: 0.07 | BZ23: RENTA | CB23: 11 | CD23: INVERSIÓN | CH23: 0.07 | CI23: PLUSVALÍA
F24: CIUDAD | G24: ZONA | H24: DESARROLLADOR | I24: DESARROLLO | J24: TIPO | K24: NIVEL | L24: VISTA | M24: TAMAÑO | N24: FINAL | O24: PRECIO | P24: BONO | Q24: % | R24: MONTO | S24: PRECIO FINAL | T24: PRECIO/M2 | U24: CAPITAL SEMILLA | V24: PROMO | X24: LOCKOFF | Y24: REC | Z24: BAÑOS | AA24: AREAS | AB24: BALCON | AD24: TERRAZA | AF24: REC | AG24: BAÑOS | AH24: AREAS | AI24: BALCON | AK24: TERRAZA | AM24: INCLUIDOS | AN24: OPCIONAL | AP24: INCLUÍDA | AQ24: TAMAÑO | AR24: OPCIONAL | AS24: TAMAÑO | AT24: PRECIO | AU24: INICIAL | AV24: MONTO | AW24: EN PLAZO | AX24: MONTO | AY24: MESES | AZ24: MENS. | BA24: TOT. ENG. | BB24: RESTO | BE24: ISAI | BF24: NOTARIO | BG24: EQUIPO | BH24: MUEBLES | BI24: TOTAL | BJ24: MONTO | BK24: INICIA | BL24: TASA | BM24: AÑOS | BN24: MENSUALIDAD | BO24: TERMINA | BP24: TOTAL | BQ24: M2 | BR24: INICIAL | BS24: FECHA | BT24: FINAL | BU24: FECHA | BV24: TOTAL | BW24: INICIAL | BX24: FECHA | BY24: TASA | BZ24: FINAL | CA24: FECHA | CB24: MESES | CC24: TOTAL | CD24: TOTAL | CE24: NETA | CF24: MENSUAL | CG24: TASA | CH24: TASA | CI24: DÍAS | CJ24: MESES | CK24: AÑOS | CL24: TOTAL | CM24: MONTO FINAL
D25: 1 | E25: Si | F25: Monterrey | G25: San José Tec | H25: AISEN | I25: Livita 20 | J25: A | K25: 4 | L25: Obispado | M25: 88 | N25: =M25+AQ25 -> 89.23 | O25: 4782888 | Q25: =R25/P25 -> #DIV/0! | R25: 100000 | S25: =P25-5+AT25 -> 79995 | T25: =S25/N25 -> 896.50342 | U25: No | V25: No | Y25: 3 | Z25: 2 | AB25: Si | AC25: 2.34 | AD25: Si | AE25: 7.8 | AF25: 3 | AG25: 2 | AI25: Si | AJ25: 2.34 | AK25: Si | AM25: 2 | AN25: Si | AO25: 180000 | AP25: Si | AQ25: 1.23 | AR25: Si | AS25: 1.23 | AT25: 80000 | AU25: 0.1 | AV25: =P25*AU25 -> 0 | AW25: 0.1 | AX25: =AW25*P25 -> 0 | AY25: 21 | AZ25: =AX25/AY25 -> 0 | BA25: =AV25+AX25 -> 0 | BB25: =1-AU25-AW25 -> 0.8 | BC25: =P25-AV25-(AY25*AZ25) -> 0 | BD25: 45597 | BE25: =S25*BE$23 -> 2399.85 | BF25: =S25*BF$23 -> 1999.875 | BG25: 300000 | BH25: 150000 | BI25: =BE25+BF25+BG25+BH25 -> 454399.72 | BJ25: =BC25 -> 0 | BK25: =BD25+31 -> 45628 | BL25: =BL$23 -> 0.105 | BM25: =BM$23 -> 15 | BN25: =PMT(BL25/12,BM25*12,-BC25) -> 0 | BO25: ='VISTAS Y USUARIOS'!BD25+('VISTAS Y USUARIOS'!BM25*365.25) -> 51075.75 | BP25: =BN25*BM25*12 -> 0 | BQ25: 40 | BR25: =M25*BQ25 -> 3520 | BS25: =BD25+31 -> 45628 | BT25: =FV(BY25,BM$23,0,-BR25) -> 9711.791 | BU25: ='VISTAS Y USUARIOS'!BD25+('VISTAS Y USUARIOS'!BM25*365.25) -> 51075.75 | BV25: =FV(BY25,BM$23,-BR25*12,0) -> 1061449.9 | BW25: 24500 | BX25: ='VISTAS Y USUARIOS'!BD25+62 -> 45659 | BY25: =BY$23 -> 0.07 | BZ25: =FV(BY25,BM$23,0,-BW25) -> 67596.273 | CA25: ='VISTAS Y USUARIOS'!BD25+('VISTAS Y USUARIOS'!BM25*365.25) -> 51075.75 | CB25: =CB$23 -> 11 | CC25: =FV(BY25,BM25,-BW25*CB25,0)-(2*BW25) -> 6723271.4 | CD25: =BA25+BI25+BP25+BV25 -> 1515849.6 | CE25: =CD25-CC25 -> -5207421.8 | CF25: =CE25/CJ25 -> -31500.154 | CG25: =(RATE(CJ25,-CF25,0,CM25))*12 -> #NUM! | CH25: =CH$23 -> 0.07 | CI25: =(BD25-TODAY()+(BM$23*365.25)) -> 5031.75 | CJ25: =CI25/30.4375 -> 165.31417 | CK25: =CJ25/12 -> 13.776181 | CL25: =INT(CK25) & " años y " & INT((CK25-INT(CK25))*12) & " meses" -> 13 años y 9 meses | CM25: =FV(CH25,((BD25-TODAY())/365.25)+BM$23,0,-S25) -> 203169.76
C26: Admin
C27: Updater
C28: Profiler
C29: Finanzas
C30: Asesor
C31: Desarrollador
A34: PROSPECTOS | D34: FECHA | E34: HORA | F34: ASESOR | G34: CIUDAD | H34: ZONA | I34: DESARROLLADOR | J34: DESARROLLO | K34: TIPOLOGÍA | L34: NOMBRE | M34: APELLIDO | N34: TELEFONO | O34: CORREO | P34: TIPO | Q34: PERFIL | R34: CÓMO LLEGA | S34: BROKER EXTERNO | T34: ESTATUS | U34: EMBUDO | V34: COMO PAGA | W34: POSITIVOS | X34: NEGATIVOS | Y34: COMENTARIOS
D35: * | E35: * | G35: * | H35: * | I35: * | J35: * | K35: * | L35: * | M35: * | N35: * | O35: * | P35: * | R35: *
C36: Admin
C37: Profiler
C38: Asesor
A41: CLIENTES | D41: FECHA | E41: HORA | F41: ASESOR | G41: NOMBRE | H41: APELLIDO | I41: TELEFONO | J41: CORREO | K41: DESARROLLADOR | L41: DESARROLLO | M41: TIPOLOGÍA | N41: PRECIO FINAL | O41: SEPARACIÓN | P41: FECHA | Q41: ENGANCHE | R41: FECHA
D42: * | E42: * | G42: * | H42: * | I42: * | J42: * | K42: * | L42: * | M42: *
C43: Admin
C44: Finanzas
C45: Asesor
C46: Desarrollador
C63: DESARROLLADORES
C64: TODO
C65: INPUT
C66: ANALISIS
C67: DESARR.
C69: DESARROLLOS
C70: TODO
C71: INPUT
... C85: DESARR.
A88: Alerta si algun prospecto esta repetido
A89: * Se registra automático al llegar por formulario

Sheet ABAJO en la LANDING
C2: Me interesa este departamento…
C3: Sabemos que para adquirir un departamento y tener ingresos por rentas se requiere pagar un enganche y un capital contra entrega, que posiblemente será un crédito hipotecario; además de los gastos de escrituración, equipo, muebles y mantenimiento mensual.
C4: Acorde a la plusvalía, se proyecta que al terminar el Crédito Hipotecario en Noviembre de 2039, este departamento tendría un valor de:
C6: =C33 -> 11590883
C20: =C22/(C23+C24+C25+C26)-1 -> 0.41807852
B22: Plusvalia | C22: =C33-D30 -> 6725086.1
B23: Enganche | C23: =[1]PDF!H17 -> 956577.6
B24: Escrituración | C24: =[1]PDF!C21+[1]PDF!D21 -> 239144.4
B25: Equipar y Amueblar | C25: =[1]PDF!F21+[1]PDF!G21 -> 450000
B26: Crédito + Mtto. - Rentas | C26: =[1]PDF!H29+[1]PDF!D33-[1]PDF!H37 -> 3096671.3
B27: Credito menos Rentas | C27: =[1]PDF!D33-[1]PDF!H37 -> 2051430.4
C29: ¿Cuánto tendría que invertir de mi bolsa?
C30: Un total de | D30: =I69-I73 -> 4865796.6 | E30: pesos de manera Paulatina durante | H30: =INT(TIPOLOGÍAS!CM3) & " años y " & INT((TIPOLOGÍAS!CM3-INT(TIPOLOGÍAS!CM3))*12) & " meses" -> 13 años y 9 meses
C32: ¿Cuál sería el valor final del departamento considerando la plusvalía?
C33: =TIPOLOGÍAS!CO3 -> 11590883 | D33: pesos
C35: ¿Qué tasa de interés necesitaría de un banco para obtener el mismo resultado?
C36: =(RATE(TIPOLOGÍAS!CL3,(((TIPOLOGÍAS!AQ3+TIPOLOGÍAS!AS3)+(TIPOLOGÍAS!BB3+TIPOLOGÍAS!BC3+TIPOLOGÍAS!BD3+TIPOLOGÍAS!BE3)+(TIPOLOGÍAS!BL3*12*TIPOLOGÍAS!$BK$1)+(TIPOLOGÍAS!BU3))-TIPOLOGÍAS!CC3)/TIPOLOGÍAS!CL3,0,-TIPOLOGÍAS!CO3,1))*12 -> 0.11488738 | D36: anual
C38: ¿Sabes de rendimientos y tasas?
C39: Te podemos compartir un analisis a detalle de todo lo que involucra la adqusición de este departamento, mismo detalle que puedes revisar en tu tiempo y posteriormente reunirnos si así lo crees conveniente para asesorarte sobre las opciones acorde a tu objetivo y posibilidades.
C40: IMAGEN EJEMPLO ESQUEMA TABLA
C42: Nombre y Apellido:
C44: Celular/Whatsapp:
C46: Correo electrónico:
D48: Solicitar Análisis
C51: ¿Cuanto tengo que pagar de ENGANCHE y cómo es el esquema?
C52: =TODAY()+15 -> 46059 | E52: En Pagos | I52: Total
C53: =TIPOLOGÍAS!AP3 -> 0.1 | D53: =TIPOLOGÍAS!AQ3 -> 478288.8 | E53: =TIPOLOGÍAS!AR3 -> 0.1 | F53: =TIPOLOGÍAS!AS3 -> 478288.8 | G53: =TIPOLOGÍAS!AT3 -> 21 | H53: =TIPOLOGÍAS!AU3 -> 22775.657 | I53: =TIPOLOGÍAS!AQ3+TIPOLOGÍAS!AS3 -> 956577.6
C55: ¿Qué gastos tengo que realizar en la ETAPA DE ENTREGA?
C56: Fecha | D56: ISAI | E56: Notario | G56: Equipar | H56: Amueblar | I56: Total
C57: =TIPOLOGÍAS!AZ3 -> 45597 | D57: =TIPOLOGÍAS!BB3 -> 143486.64 | E57: =TIPOLOGÍAS!BC3 -> 95657.76 | G57: =TIPOLOGÍAS!BD3 -> 300000 | H57: =TIPOLOGÍAS!BE3 -> 150000 | I57: =TIPOLOGÍAS!BB3+TIPOLOGÍAS!BC3+TIPOLOGÍAS!BD3+TIPOLOGÍAS!BE3 -> 689144.4
C59: ¿Cuanto ocupo de CRÉDITO HIPOTECARIO y como se paga?
C60: Monto | E60: Plazo | F60: Tasa | G60: Mensualidad | I60: Total
C61: =(TIPOLOGÍAS!R3-TIPOLOGÍAS!AQ3-TIPOLOGÍAS!AS3)/TIPOLOGÍAS!R3 -> 0.79572913 | D61: =TIPOLOGÍAS!AX3 -> 3826310.4 | E61: =TIPOLOGÍAS!BK$1 -> 15 | F61: =TIPOLOGÍAS!BJ$1 -> 0.12 | G61: =TIPOLOGÍAS!BL3 -> 45922.155 | I61: =TIPOLOGÍAS!BK$1*12*TIPOLOGÍAS!BL3 -> 8265988
C63: ¿Cuánto costará el MANTENIMIENTO durante todo el Crédito Hipotecario?
C64: Al inicio | F64: Al terminar el Crédito | I64: Total
C65: =TIPOLOGÍAS!AZ3+31 -> 45628 | D65: =TIPOLOGÍAS!BQ3 -> 3520 | G65: =TIPOLOGÍAS!AZ3+(TIPOLOGÍAS!BK$1*365.25) -> 51075.75 | H65: =TIPOLOGÍAS!BS3 -> 8841.7901 | I65: =TIPOLOGÍAS!BU3 -> 1045240.9
C67: ¿Cuánto es el TOTAL DE INVERSIÓN desde el Enganche hasta que se termina de pagar el Crédito?
C68: Enganche | D68: Etapa Entrega | E68: Crédito Hipotecario | G68: Mantenimiento | I68: Total
C69: =TIPOLOGÍAS!AQ3+TIPOLOGÍAS!AS3 -> 956577.6 | D69: =TIPOLOGÍAS!BB3+TIPOLOGÍAS!BC3+TIPOLOGÍAS!BD3+TIPOLOGÍAS!BE3 -> 689144.4 | E69: =TIPOLOGÍAS!BK$1*12*TIPOLOGÍAS!BL3 -> 8265988 | G69: =TIPOLOGÍAS!BU3 -> 1045240.9 | I69: =I53+I57+I61+I65 -> 10956951
C71: ¿Cuál es la expectativa de INGRESOS POR RENTAS?
C72: Al inicio | E72: Al terminar el Crédito | I72: Total
C73: =TIPOLOGÍAS!AZ3+62 -> 45659 | D73: =TIPOLOGÍAS!BW3 -> 23000 | E73: =TIPOLOGÍAS!AZ3+(TIPOLOGÍAS!BK$1*365.25) -> 51075.75 | G73: =TIPOLOGÍAS!BZ3 -> 61701.628 | I73: =TIPOLOGÍAS!CC3-(TIPOLOGÍAS!BZ3*2) -> 6091154.3
C75: ¿Cuanto es lo que REALMENTE INVERTÍ de mi bolsa?
C76: Inversión Total | D76: Ingresos por Rentas | F76: Inversión Real | H76: Tiempo | I76: Inversion Mensual Promedio
C77: =I69 -> 10956951 | D77: =I73 -> 6091154.3 | F77: =C77-D77 -> 4865796.6 | H77: =INT(TIPOLOGÍAS!CM3) & " años y " & INT((TIPOLOGÍAS!CM3-INT(TIPOLOGÍAS!CM3))*12) & " meses" -> 13 años y 9 meses | I77: =F77/TIPOLOGÍAS!CL3 -> 29433.633

Sheet Con Prom.
E1: 5
A8: =UPPER("proyecto "&(VLOOKUP($E$1,TIPOLOGÍAS!$B:$AA,6,FALSE))) -> PROYECTO LÍVITA 20
A9: =VLOOKUP($E$1,TIPOLOGÍAS!$B:$DC,12,FALSE)&" m2" -> 88 m2 | B9: ="Vista "&VLOOKUP($E$1,TIPOLOGÍAS!$B:$DC,10,FALSE) -> Vista Obispado | D9: =VLOOKUP($E$1,TIPOLOGÍAS!$B:$DC,23,FALSE)&" Recámaras" -> 2 Recámaras | E9: 1 Balcón
A10: =VLOOKUP($E$1,TIPOLOGÍAS!$B:$DC,17,FALSE) -> 5477582 | B10: ="Nivel "&VLOOKUP($E$1,TIPOLOGÍAS!$B:$DC,9,FALSE) -> Nivel 4 | D10: 1 Flex | E10: 1 Terraza
A11: =TEXT(VLOOKUP($E$1,TIPOLOGÍAS!$B:$DC,18,FALSE),"$0,0")&" /m2" -> $62,245 /m2 | B11: ="Tipo "&VLOOKUP($E$1,TIPOLOGÍAS!$B:$DC,8,FALSE) -> Tipo A | D11: =VLOOKUP($E$1,TIPOLOGÍAS!$B:$DC,25,FALSE)&" Baños" -> 2 Baños | E11: 2 Cajones
A12: ="Ubicado en "&VLOOKUP($E$1,TIPOLOGÍAS!$B:$AA,3,FALSE)&" en la Zona "&VLOOKUP($E$1,TIPOLOGÍAS!$B:$DC,4,FALSE)&", para entrega en Nov 2025" -> Ubicado en Monterrey en la Zona San José Tec, para entrega en Nov 2025
A14: ENGANCHE Y SETUP
A15: ="Enganche del "&TEXT(VLOOKUP($E$1,TIPOLOGÍAS!$B:$DC,39,FALSE),"0%")&" en "&TEXT(TODAY()+15,"mmm aa") -> Enganche del 0% en Feb aa | B15: =VLOOKUP($E$1,TIPOLOGÍAS!$B:$DC,42,FALSE) -> 821637.3
A16: =TEXT(VLOOKUP($E$1,TIPOLOGÍAS!$B:$DC,41,FALSE),"0%")&" en plazo a "&VLOOKUP($E$1,TIPOLOGÍAS!$B:$DC,43,FALSE)&" meses de "&TEXT(VLOOKUP($E$1,TIPOLOGÍAS!$B:$DC,44,FALSE),"$0,0") -> 15% en plazo a 0.15 meses de $821,637 | B16: =VLOOKUP($E$1,TIPOLOGÍAS!$B:$DC,42,FALSE) -> 821637.3
A17: ="Escrituración en "&TEXT(VLOOKUP($E$1,TIPOLOGÍAS!$B:$DC,49,FALSE),"mmm aa")&": " -> #VALUE! | B17: =(VLOOKUP($E$1,TIPOLOGÍAS!$B:$DC,52,FALSE))+(VLOOKUP($E$1,TIPOLOGÍAS!$B:$DC,51,FALSE)) -> 45931
A18: Equipamiento y Amueblar: | B18: =(VLOOKUP($E$1,TIPOLOGÍAS!$B:$DC,53,FALSE))+(VLOOKUP($E$1,TIPOLOGÍAS!$B:$DC,54,FALSE)) -> 273879.1
A19: ="En "&VLOOKUP($E$1,TIPOLOGÍAS!$B:$DC,43,FALSE)+3&" meses:" -> En 3.15 meses: | B19: =SUM(B15:B18) -> 1963084.7
B20: ="Promedio mensual de "&TEXT(B19/(VLOOKUP($E$1,TIPOLOGÍAS!$B:$DC,43,FALSE)+3),"$0,0") -> Promedio mensual de $623,201
A22: CRÉDITO Y MANTENIMIENTO | D22: FLUJO AL INICIO Y FIN DEL CRÉDITO
A23: =TEXT(VLOOKUP($E$1,TIPOLOGÍAS!$B:$DC,46,FALSE),"0,0%")&" restante a "&VLOOKUP($E$1,TIPOLOGÍAS!$B:$DC,60,FALSE)&" años" -> 3,912,559% restante a 45962 años | B23: =VLOOKUP($E$1,TIPOLOGÍAS!$B:$DC,57,FALSE) -> 763879.1 | D23: ="Renta al iniciar el crédito en "&TEXT(VLOOKUP($E$1,TIPOLOGÍAS!$B:$DC,73,FALSE),"mmm aaa") -> Renta al iniciar el crédito en ene 1900 | E23: =VLOOKUP($E$1,TIPOLOGÍAS!$B:$DC,72,FALSE) -> 1175896
A24: ="Con Tasa del "&TEXT(VLOOKUP($E$1,TIPOLOGÍAS!$B:$DC,59,FALSE),"00.00%")&" son "&TEXT(VLOOKUP($E$1,TIPOLOGÍAS!$B:$DC,61,FALSE),"$0,0")&" x "&VLOOKUP($E$1,TIPOLOGÍAS!$B:$DC,60,FALSE)*12&" meses:" -> Con Tasa del 383430740.00% son $00 x 551544 meses: | B24: =VLOOKUP($E$1,TIPOLOGÍAS!$B:$DC,63,FALSE) -> 46018.133 | D24: Costo del crédito y mantenimiento: | E24: =(VLOOKUP($E$1,TIPOLOGÍAS!$B:$DC,61,FALSE))+VLOOKUP($E$1,TIPOLOGÍAS!$B:$DC,66,FALSE) -> 0.12
A25: ="Mtto. en "& TEXT(VLOOKUP($E$1,TIPOLOGÍAS!$B:$DC,67,FALSE),"mmm aaa") -> Mtto. en feb 1900 | B25: =VLOOKUP($E$1,TIPOLOGÍAS!$B:$DC,66,FALSE) -> 0 | D25: Diferencia: | E25: =E23-E24 -> 1175895.9
A26: ="Mtto. en "& TEXT(VLOOKUP($E$1,TIPOLOGÍAS!$B:$DC,69,FALSE),"mmm aaa")&" con inflación del "&TEXT(TIPOLOGÍAS!BY1,"0.0%") -> Mtto. en nov 2025 con inflación del 6.8% | B26: =VLOOKUP($E$1,TIPOLOGÍAS!$B:$DC,68,FALSE) -> 3960 | D26: ="Renta al finalizar el crédito en "&TEXT(VLOOKUP($E$1,TIPOLOGÍAS!$B:$DC,76,FALSE),"mmm aaa") -> Renta al finalizar el crédito en ene 1900 | E26: =VLOOKUP($E$1,TIPOLOGÍAS!$B:$DC,75,FALSE) -> 45993
A27: ="Total de mantenimiento en "&VLOOKUP($E$1,TIPOLOGÍAS!$B:$DC,60,FALSE)&" años" -> Total de mantenimiento en 45962 años | B27: =VLOOKUP($E$1,TIPOLOGÍAS!$B:$DC,70,FALSE) -> 9947.0139 | D27: Costo del crédito y mantenimiento: | E27: =(VLOOKUP($E$1,TIPOLOGÍAS!$B:$DC,61,FALSE))+VLOOKUP($E$1,TIPOLOGÍAS!$B:$DC,68,FALSE) -> 3960.12
A28: ="En "&((VLOOKUP($E$1,TIPOLOGÍAS!$B:$DC,60,FALSE))&" años:") -> En 45962 años: | B28: =B24+B27 -> 55965.147 | D28: Diferencia: | E28: =E26-E27 -> 42032.88
B29: ="Promedio mensual de "&TEXT((B28/VLOOKUP($E$1,TIPOLOGÍAS!$B:$DC,60,FALSE)/12),"$0,0") -> Promedio mensual de $00
A32: INGRESOS Y EGRESOS TOTALES | D32: VALOR DE LA PROPIEDAD
A33: ="Egresos en "&TEXT((((VLOOKUP($E$1,TIPOLOGÍAS!$B:$DC,60,FALSE))*12+(VLOOKUP($E$1,TIPOLOGÍAS!$B:$DC,43,FALSE)+3))/12),"0.0")&" años:" -> Egresos en 45962.3 años: | B33: =B19+B28 -> 2019049.8 | D33: =TEXT(VLOOKUP($E$1,TIPOLOGÍAS!$B:$DC,76,FALSE),"mmm aaa")&" con plusvalía anual del "&TEXT(TIPOLOGÍAS!BY1,"0.0%")&":" -> ene 1900 con plusvalía anual del 6.8%: | E33: =VLOOKUP($E$1,TIPOLOGÍAS!$B:$DC,90,FALSE) -> 14.690623
B34: ="Promedio mensual de: "&TEXT((B33/((VLOOKUP($E$1,TIPOLOGÍAS!$B:$DC,60,FALSE))*12+(VLOOKUP($E$1,TIPOLOGÍAS!$B:$DC,43,FALSE)+3))),"$0,0") -> Promedio mensual de: $04 | D34: Tasa anual acorde a la inversión real: | E34: =RATE((((VLOOKUP($E$1,TIPOLOGÍAS!$B:$DC,60,FALSE))*12+(VLOOKUP($E$1,TIPOLOGÍAS!$B:$DC,43,FALSE)+3))),B37/VLOOKUP($E$1,TIPOLOGÍAS!$B:$DC,60,FALSE)/12,,E33)*12 -> #NUM!
A35: ="Ingresos en "&VLOOKUP($E$1,TIPOLOGÍAS!$B:$DC,60,FALSE)&" años al "&TEXT((TIPOLOGÍAS!CB1/12),"0%")&" de ocupación:" -> Ingresos en 45962 años al 92% de ocupación: | B35: =VLOOKUP($E$1,TIPOLOGÍAS!$B:$DC,78,FALSE) -> 51409.75 | D35: La propiedad se rentará en: | E35: =VLOOKUP($E$1,TIPOLOGÍAS!$B:$DC,75,FALSE) -> 45993
B36: ="Promedio mensual de: "&TEXT((B35/VLOOKUP($E$1,TIPOLOGÍAS!$B:$DC,60,FALSE))/12,"$0,0") -> Promedio mensual de: $00
A37: Ingresos menos egresos: | B37: =B35-B33 -> -1967640.1
B38: ="Promedio mensual en "&TEXT((((VLOOKUP($E$1,TIPOLOGÍAS!$B:$DC,60,FALSE))*12+(VLOOKUP($E$1,TIPOLOGÍAS!$B:$DC,43,FALSE)+3))/12),"0.0")&" años: " &TEXT(B37/VLOOKUP($E$1,TIPOLOGÍAS!$B:$DC,60,FALSE)/12,"$0,0") -> Promedio mensual en 45962.3 años: -$04

Sheet CAT Propiedades
Y1: Iconos
C2: CIUDADES | E2: ZONAS | H2: DESARROLLADORES | J2: DESARROLLOS | L2: VISTA 1 | M2: VISTA 2 | N2: VISTA 3 | O2: VISTA 4 | P2: VISTA 5 | Q2: VISTA 6 | V2: TIPO DE DESARROLLO | Y2: AMENIDADES | AA2: EFICIENCIA | AC2: OTROS | AE2: VALOR | AG2: COMO SE ENTREGAN | AI2: COMERCILIZADORAS | AK2: SI /NO | AO2: INCREMENTO RENTA | AV2: CRÉDITO AÑOS | AY2: CIUDADES | BJ2: DESARROLLADORES | BT2: DESARROLLADORES
A3: 1 | C3: =Monterrey[[#Headers],[Monterrey]] -> Monterrey | E3: Monterrey | F3: Centro | H3: =AISEN[[#Headers],[AISEN]] -> AISEN | J3: Koinox | K3: Kyo Constella | L3: Centro | M3: Sur | N3: Centro | O3: Centro | P3: San José Tec | Q3: Sur | Y3: Alberca | AA3: Centros de lavado | AC3: Personal de Seguridad | AE3: Redacciones del desarrollo y su concepto, ejemplo: | AG3: Muros Interiores en Yeso | AI3: Birlok | AO3: 0.04 | AP3: 0.05 | AQ3: 0.06 | AR3: 0.07 | AS3: 0.08 | AT3: 0.09 | AV3: 5 | AY3: Monterrey | AZ3: Saltillo | BA3: Guadalajara | BB3: CDMX | BC3: C.5 | BD3: C.6 | BE3: C.7 | BF3: C.8 | BG3: C.9 | BH3: C.10 | BJ3: AISEN | BK3: ALTIO | BL3: BIRLOK | BM3: _C3CO | BN3: CAPITEL | BO3: CARZA | BP3: CREARE | BQ3: CUADRO | BR3: DELTA | BS3: IDEI | BT3: KOINOX | BU3: LANDWORK | BV3: NEST | BW3: PISSA | BX3: PROYECTOS9 | BY3: QUANTIUM | BZ3: TROY | CA3: VALO | CB3: NEUBEN | CC3: D20 | CD3: D21 | CE3: D22 | CF3: D23 | CG3: D24 | CH3: D25 | CI3: D26 | CJ3: D27 | CK3: D28 | CL3: D29 | CM3: D30 | CN3: D31 | CO3: D32 | CP3: D33 | CQ3: D34 | CR3: D35 | CS3: D36 | CT3: D37 | CU3: D38 | CV3: D39 | CW3: D40 | CX3: D41 | CY3: D42 | CZ3: D43 | DA3: D44 | DB3: D45 | DC3: D46 | DD3: D47 | DE3: D48 | DF3: D49 | DG3: D50
A4: 2 | C4: =Saltillo[[#Headers],[Saltillo]] -> Saltillo | E4: Monterrey | F4: Poniente | H4: =ALTIO[[#Headers],[ALTIO]] -> ALTIO | J4: IDEI | K4: Novus | L4: Poniente | M4: San Nicolás | N4: Centro | O4: Poniente | P4: Fundidora | Q4: San Nicolás | V4: Residencial | Y4: Arenero | AA4: Community Closet | AC4: Video Vigilancia / CCTV | AG4: Muros Interiores en Concreto Aparente | AI4: NUMA | AK4: Si | AM4: AÑOS | AN4: 5 | AO4: 1.0832645 | AP4: 1.1051263 | AQ4: 1.1274186 | AR4: 1.1501478 | AS4: 1.1733202 | AT4: 1.1969421 | AV4: 10 | AY4: Valle | AZ4: Centro | BA4: AAA | BB4: DDD | BC4: z51 | BD4: z61 | BE4: z71 | BF4: z81 | BG4: z91 | BH4: z101 | BJ4: Livita 20 | BK4: Arena Fundidora | BL4: Colonia | BM4: Alika | BN4: The Village | BO4: Altana | BP4: Aldea Sur | BQ4: Nogales | BR4: Distrito Domo | BS4: Avalon | BT4: Constella | BU4: Mun | BV4: Rise | BW4: Barrio W | BX4: Sohl | BY4: Akira | BZ4: Gaia | CA4: Montevo | CB4: Aria
A5: 3 | C5: =Guadalajara[[#Headers],[Guadalajara]] -> Guadalajara | E5: Monterrey | F5: Valle Poniente | H5: =BIRLOK[[#Headers],[BIRLOK]] -> BIRLOK | J5: IDEI | K5: Avalon | L5: Valle Poniente | M5: Valle Oriente | N5: Poniente | O5: Valle Poniente | P5: Galerías | Q5: Valle Oriente | V5: Comercial | Y5: Asadores | AA5: Cuarto de herramientas | AC5: Control de acceso vehicular | AG5: Muros Interiores con Acabado Ladrillo | AI5: CREAM | AK5: No | AN5: 10 | AO5: 1.2006107 | AP5: 1.2577893 | AQ5: 1.3180795 | AR5: 1.3816448 | AS5: 1.4486562 | AT5: 1.519293 | AV5: 15 | AY5: Valle Oriente | AZ5: Sur | BA5: BBB | BB5: EEE | BC5: z52 | BD5: z62 | BE5: z72 | BF5: z82 | BG5: z92 | BH5: z102 | BJ5: - | BK5: Arena Calzada | BL5: - | BM5: - | BN5: - | BO5: Cantera | BP5: - | BQ5: - | BR5: Las Fridas | BS5: Lativ | BT5: Aluna | BU5: - | BV5: Top | BW5: - | BX5: Lalo | BY5: Alejandría | BZ5: - | CA5: - | CB5: -
A6: 4 | C6: =CDMX[[#Headers],[CDMX]] -> CDMX | E6: Monterrey | F6: Valle | H6: =_C3CO[[#Headers],[_C3CO]] -> _C3CO | J6: ALTIO | K6: Arena Fundidora | L6: Valle | M6: Maria Luisa | N6: Valle Poniente | O6: Valle | P6: Morones | Q6: Maria Luisa | V6: Oficinas | Y6: Bungalows Culinarios | AA6: Lavanderia | AC6: Accesos independientes | AG6: Cielo de Plafond | AK6: Tal Vez | AN6: 15 | AO6: 1.3349058 | AP6: 1.4385709 | AQ6: 1.5517313 | AR6: 1.6752681 | AS6: 1.8101409 | AT6: 1.9573944 | AV6: 20 | AY6: Valle Poniente | AZ6: Norte | BA6: CCC | BB6: FFF | BC6: z53 | BD6: z63 | BE6: z73 | BF6: z83 | BG6: z93 | BH6: z103 | BK6: - | BL6: - | BO6: - | BQ6: - | BR6: Via Cordillera | BS6: Saqqara | BT6: Midtown | BU6: - | BV6: West | BX6: Lola | BY6: Alaia
A7: 5 | C7: =C.5[[#Headers],[C.5]] -> C.5 | E7: Monterrey | F7: Sur | H7: =CAPITEL[[#Headers],[CAPITEL]] -> CAPITEL | J7: ALTIO | K7: Arena Calzada | L7: Sur | M7: San José Tec | N7: Valle | O7: Centro | P7: Valle Poniente | Q7: San José Tec | V7: Salud | Y7: Cancha de Futbol | AA7: Rack de Bicicletas | AG7: Piso Cerámico | AN7: 20 | AO7: 1.4889039 | AP7: 1.6532977 | AQ7: 1.8392796 | AR7: 2.0497746 | AS7: 2.2880982 | AT7: 2.558006 | AY7: La Huasteca | AZ7: - | BC7: z54 | BD7: z64 | BE7: z74 | BF7: z84 | BG7: z94 | BH7: z104 | BL7: - | BO7: - | BQ7: - | BR7: - | BS7: Novus | BT7: - | BV7: F1rst | BX7: Moca Verde | BY7: -
A8: 6 | C8: =C.6[[#Headers],[C.6]] -> C.6 | E8: Monterrey | F8: San Nicolás | H8: =CARZA[[#Headers],[CARZA]] -> CARZA | J8: PROYECTOS 9 | K8: Lalo | L8: San Nicolás | M8: Fundidora | N8: Valle | O8: Poniente | P8: Valle | Q8: Fundidora | Y8: Cancha Polivalente | AA8: Suite de invitados | AG8: Piso Porcelanato | AY8: Las Torres | BC8: z55 | BD8: z65 | BE8: z75 | BF8: z85 | BG8: z95 | BH8: z105 | BL8: - | BQ8: - | BS8: - | BT8: - | BV8: - | BX8: Moca Amarillo | BY8: -
A9: 7 | C9: =C.7[[#Headers],[C.7]] -> C.7 | E9: Monterrey | F9: Valle Oriente | H9: =CREARE[[#Headers],[CREARE]] -> CREARE | J9: PROYECTOS 9 | K9: Lola | L9: Valle Oriente | M9: Galerías | N9: Valle | O9: Valle Poniente | P9: Maria Luisa | Q9: Galerías | Y9: Cine al Aire Libre | AA9: shoot de basura | AG9: Piso en Concreto Pulido | AY9: Carretera | BC9: z56 | BD9: z66 | BE9: z76 | BF9: z86 | BG9: z96 | BH9: z106 | BS9: - | BT9: - | BV9: - | BX9: Moca Naranja
A10: 8 | C10: =C.8[[#Headers],[C.8]] -> C.8 | E10: Monterrey | F10: Maria Luisa | H10: =CUADRO[[#Headers],[CUADRO]] -> CUADRO | J10: PROYECTOS 9 | K10: Moca Azul | L10: Maria Luisa | M10: Morones | N10: Sur | O10: Valle | P10: San José Tec | Q10: San José Tec | Y10: Co-work | AA10: Elevadores | AG10: Zoclo | AY10: Sur | BC10: z57 | BD10: z67 | BE10: z77 | BF10: z87 | BG10: z97 | BH10: z107 | BS10: - | BX10: Moca Azul
A11: 9 | C11: =C.9[[#Headers],[C.9]] -> C.9 | E11: Monterrey | F11: San José Tec | H11: =DELTA[[#Headers],[DELTA]] -> DELTA | J11: PROYECTOS 9 | K11: Moca Verde | L11: San José Tec | N11: San Nicolás | O11: Valle Oriente | P11: Fundidora | Q11: Fundidora | Y11: fogateros | AE11: Espectaculares vistas | AG11: Pintura | AY11: Tec | BC11: z58 | BD11: z68 | BE11: z78 | BF11: z88 | BG11: z98 | BH11: z108 | BX11: -
A12: 10 | C12: =C.10[[#Headers],[C.10]] -> C.10 | E12: Monterrey | F12: Fundidora | H12: =IDEI[[#Headers],[IDEI]] -> IDEI | J12: PROYECTOS 9 | K12: Moca Rojo | L12: Fundidora | M12: Centro | N12: Valle Oriente | O12: Maria Luisa | P12: Galerías | Q12: Galerías | Y12: Gimnasio | AE12: Pet Friendly | AG12: Ventanería de Aluminio | AI12: DESPACHOS DE ARQUITECTURA | AY12: Fundidora | BC12: z59 | BD12: z69 | BE12: z79 | BF12: z89 | BG12: z99 | BH12: z109 | BX12: -
A13: 11 | E13: Monterrey | F13: Galerías | H13: =KOINOX[[#Headers],[KOINOX]] -> KOINOX | J13: PLATE | K13: Colonia | L13: Galerías | M13: Poniente | N13: Maria Luisa | O13: San José Tec | P13: Morones | Q13: Morones | Y13: Golfito | AE13: Puntos de interés | AG13: Ventanería de Aluminio Duo Vent | AI13: Perez y Perez Arquitectos | AY13: Centro | BC13: z60 | BD13: z70 | BE13: z80 | BF13: z90 | BG13: z100 | BH13: z110
A14: 12 | E14: Monterrey | F14: Morones | H14: =LANDWORK[[#Headers],[LANDWORK]] -> LANDWORK | J14: CUADRO | K14: Nogales | L14: Morones | M14: Valle Poniente | N14: San José Tec | O14: Fundidora | P14: Centro | Q14: Morones | V14: NIVEL | W14: MTTO. | Y14: Grill Patio | AE14: Ubicación | AG14: Puerta Principal con Chapa | AY14: Mitras
A15: 13 | E15: Monterrey | F15: Constitución | H15: =NEST[[#Headers],[NEST]] -> NEST | J15: LANDWORK | K15: Mun | L15: Constitución | M15: Valle | N15: Fundidora | O15: Galerías | P15: Poniente | Q15: Morones | V15: AAA | W15: 35 | Y15: Jardín de Hamacas | AE15: Estilo Neoyorkino | AG15: Puertas interiores con Chapa | AY15: Obispado
A16: 14 | E16: Monterrey | F16: Carretera | H16: =PISSA[[#Headers],[PISSA]] -> PISSA | J16: NEST | K16: Rise | L16: Carretera | M16: Valle | N16: Galerías | O16: Morones | P16: Valle Poniente | Q16: Morones | V16: A | W16: 45 | Y16: Jardin Zen | AE16: Lobby exclusivo para cada torre | AG16: Iluminación, Contactos y Apagadores | AY16: Morones
A17: 15 | E17: Monterrey | F17: Guadalupe | H17: =PROYECTOS9[[#Headers],[PROYECTOS9]] -> PROYECTOS9 | J17: QUANTIUM | K17: Akira | L17: Guadalupe | M17: Valle | N17: Morones | O17: Morones | P17: Valle | Q17: Morones | V17: B | W17: 65 | Y17: Juegos Infantiles | AG17: Lavanetas con Grifería | AY17: Constitución
A18: 16 | E18: Monterrey | F18: Obispado | H18: =QUANTIUM[[#Headers],[QUANTIUM]] -> QUANTIUM | V18: C | W18: 80 | Y18: Ludoteca | AG18: Sanitarios | AY18: Cumbres
A19: 17 | E19: Monterrey | F19: Contry | H19: =TROY[[#Headers],[TROY]] -> TROY | Y19: Palapa Techada | AG19: Manerales y Cebolletas para Regaderas | AY19: Santa Maria
A20: 18 | E20: Monterrey | F20: Cumbres | H20: =VALO[[#Headers],[VALO]] -> VALO | V20: NIVELES | Y20: Parque Canino | AG20: Preparaciones listas para Mini Split | AY20: San Nicolas
A21: 19 | H21: =NEUBEN[[#Headers],[NEUBEN]] -> NEUBEN | V21: 1 | Y21: Reading Room | AG21: Cocina | AY21: Universidad
A22: 20 | V22: 2 | Y22: Sala de Cine | AG22: Canceles | AY22: Guadalupe
A23: 21 | V23: 3 | Y23: Sala de Juegos | AG23: Closets | AY23: Santa Catarina
A24: 22 | V24: 4 | Y24: Sala de Karaoke | AG24: Aire Acondicionado | AY24: Escobedo
A25: 23 | V25: 5 | Y25: Sala de Visitas | AY25: Apodaca
A26: 24 | V26: 6 | Y26: Salon Culnario | AY26: Juarez
A27: 25 | V27: 7 | Y27: Salon de Eventos | AY27: García
A28: 26 | V28: 110 | Y28: Salon de Reuniones
A29: 27 | Y29: Sky Lounge
A30: 28 | V30: TORRES | Y30: Social Gym
A31: 29 | V31: 1 | Y31: Sports Bar
A32: 30 | V32: 2 | Y32: Terraza
A33: 31 | V33: 3 | Y33: Vitapista
A34: 32 | V34: 4 | Y34: Yoga Room
A35: 33 | V35: 5
A36: 34 | V36: 6
A37: 35 | V37: 7
A38: 36 | V38: 8
A39: 37
A40: 38 | V40: RECÁMARAS
A41: 39 | V41: Loft
A42: 40 | V42: 1
A43: 41 | V43: 1 + Flex
A44: 42 | V44: 2
A45: 43 | V45: 2 + Flex
A46: 44 | V46: 3
A47: 45 | V47: 3 + Flex
A48: 46 | V48: 4
A49: 47 | V49: 4 + Flex
A50: 48
A51: 49 | V51: BAÑOS
A52: 50 | V52: 1
V53: 1.5
V54: 2
V55: 2.5
V56: 3
V57: 3.5
V59: CAJONES
V60: No
V61: 1
V62: 2
V63: 3
V64: 2 en Tandem
V66: AREAS
V67: Sala
V68: Comedor
V69: Cocina
V70: Lavandería
V71: Servicio

Sheet CAT Prospectos
B1: TIPO | C1: PERFIL | D1: FUENTE | E1: ASESOR | F1: SI ES BROKER EXTERNO | G1: ESTATUS | H1: ETAPA DE EMBUDO | I1: COMO PAGA | J1: POSITIVOS | K1: NEGATIVOS
B2: Inversionista | C2: Estudiante | D2: INSTAGRAM ADS | E2: Asesor 1 | F2: Externo 1 | G2: ACTIVO | H2: NUEVO | I2: ENGANCHE BAJO | J2: PRECIO | K2: PRECIO
B3: Uso Propio | C3: Profesionista | D3: INSTAGRAM FOLLOWER | E3: Asesor 2 | F3: Externo 2 | G3: EN HOLD | H3: ASIGNADO | I3: ENGANCHE ALTO | J3: UBICACIÓN | K3: UBICACIÓN
B4: Revender | C4: Pareja | D4: FACEBOOK ADS | E4: Asesor 3 | F4: Externo 3 | G4: NO ACTIVO | H4: VALIDADO | I4: CAPITAL SEMILLA | J4: DISEÑO | K4: DISEÑO
C5: Familia Joven | D5: FACEBOOK FAN | E5: Asesor 4 | F5: Externo 4 | H5: ENVÍO DE INFO | J5: TAMAÑO | K5: TAMAÑO
C6: Familia Grande | D6: LANDING PAGE | H6: MUESTRA INTERÉS | J6: AMENIDADES | K6: AMENIDADES
C7: Tercera Edad | D7: GRUPO FACEBOOK | H7: PRESENTACIÓN | J7: ESQUEMA DE PAGOS | K7: ESQUEMA DE PAGOS
D8: FB MARKETPLACE | H8: SHOWROOM | K8: PERMISOS
D9: BROKER EXTERNO | H9: EVALUANDO | K9: DESARROLLADOR
D10: REFERIDO | H10: NEGOCIACIÓN | K10: TIEMPO DE ENTREGA
D11: LEAD PASADO | H11: CIERRE GANADO
D12: CONOCIDO DE ASESOR | H12: SEPARADO
D13: BASE DE DATOS | H13: ENGANCHE Y FIRMA
D14: PERIÓDICO | H14: CIERRE PERDIDO
D15: FLYER | H15: NO CONTESTA
D16: RÓTULO | H16: NO LE INTERESÓ
D17: GOOGLE ADS
D18: LINKEDIN
D19: TIK TOK
D20: TWITTER
